[
	{
		"id": "book_001",
		"status": "ADVANCE_PAID",
		"user_id": "cl12345abcde",
		"trip_id": "trip_0001",
		"product_id": "IN_H1QHK1RSOD",
		"company_id": "company_0001",
		"participants": [
			{
				"id": "kid_0001",
				"city": "Warszawa",
				"type": "KID",
				"email": null,
				"pesel": "12345678901",
				"phone": null,
				"street": "Ulica ABC",
				"illness": false,
				"alergies": false,
				"postcode": "00-001",
				"province": "mazowieckie",
				"vaccines": [],
				"diagnosis": false,
				"full_name": "Adam Kowalski",
				"is_delete": 0,
				"last_name": "Kowalski",
				"medicines": false,
				"parent_id": null,
				"surgeries": false,
				"birth_date": "2020-01-01",
				"disability": false,
				"first_name": "Adam",
				"house_number": "10",
				"maladjustment": false,
				"owner_user_id": "cl12345abcde",
				"street_number": "5",
				"medicines_dose": null,
				"medicines_name": null,
				"surgeries_date": null,
				"medicines_cause": null,
				"surgeries_cause": null,
				"ag_state_version": 1,
				"illness_symptoms": null,
				"alergies_symptoms": null,
				"other_information": null,
				"diagnosis_symptoms": null,
				"illness_description": null,
				"alergies_description": null,
				"diagnosis_description": null,
				"surgeries_desctiption": null,
				"disability_description": null,
				"maladjustment_description": null
			}
		],
		"created_at": "2025-01-01T09:00:00.000Z",
		"total_price": 1200,
		"payable_price": 1200,
		"discount_amount": 0,
		"deleted_at": null,
		"ag_state_version": 3,
		"trip_data": {
			"id": "trip_0001",
			"name": "Kolonie w górach",
			"status": "ACTIVE",
			"advance": 300,
			"company": {
				"id": "company_0001",
				"name": "Górska Przygoda"
			},
			"max_age": 18,
			"min_age": 7,
			"product": {
				"id": "PR_0001",
				"name": "Kolonie 2025",
				"type": "kolonie"
			},
			"bookings": [],
			"end_date": "2025-07-15",
			"max_count": 10,
			"min_count": 1,
			"company_id": "company_0001",
			"created_at": "2024-12-01T09:00:00.000Z",
			"full_price": 1200,
			"is_deleted": false,
			"product_id": "PR_0001",
			"start_date": "2025-07-01",
			"archived_at": null,
			"is_archived": false,
			"product_type": "kolonie",
			"available_spots": 9,
			"ag_state_version": 1,
			"reservation_price": 1200,
			"advance_conditions": null,
			"reservation_min_days": null,
			"discounts_description": null,
			"full_price_conditions": null
		},
		"product_data": {
			"id": "IN_H1QHK1RSOD",
			"name": "Kolonie 2025",
			"type": "kolonie",
			"files": null,
			"media": null,
			"trips": [],
			"status": "ACTIVE",
			"company": {
				"id": "company_0001",
				"name": "Górska Przygoda",
				"fc_website_url": null,
				"logo_image_url": null
			},
			"max_age": 18,
			"min_age": 7,
			"location": {
				"city": "Zakopane",
				"street": "Ul. Górska",
				"province": "małopolskie",
				"post_code": "34-500",
				"room_number": "101",
				"house_number": "15"
			},
			"food_type": null,
			"is_delete": false,
			"trip_type": null,
			"attributes": null,
			"company_id": "company_0001",
			"created_at": "2024-12-01T09:00:00.000Z",
			"food_vegan": null,
			"is_archive": false,
			"main_photo": {
				"id": "photo_0001",
				"url": "http://example.com/photo1.jpg",
				"width": 1700,
				"height": 1134,
				"provider": "cloudinary",
				"providerData": {}
			},
			"archived_at": null,
			"description": "Kolonie w górach 2025",
			"location_id": null,
			"country_code": "PL",
			"country_name": "Polska",
			"pickup_route": null,
			"published_at": null,
			"admin_comment": null,
			"category_code": null,
			"file_sections": null,
			"location_name": null,
			"transport_type": "autokar",
			"food_vegetarian": null,
			"transport_route": null,
			"ag_state_version": 1,
			"food_description": null,
			"subcategory_code": null,
			"admin_approved_at": null,
			"transport_vehicle": "Mercedes-Benz Tourismo",
			"additional_info_text": null,
			"conditions_text_long": null,
			"schedule_description": null,
			"amenities_description": null,
			"conditions_text_short": null,
			"insurance_description": null,
			"transport_description": null,
			"admin_show_on_home_page": null,
			"participation_conditions": null,
			"participation_description": null,
			"admin_promote_on_home_page": null
		},
		"parent": {
			"id": "parent_0001",
			"city": "Warszawa",
			"type": "PARENT",
			"email": "rodzic@example.com",
			"pesel": null,
			"phone": "123456789",
			"street": "Ulica Nowa",
			"illness": false,
			"alergies": false,
			"postcode": "00-001",
			"province": "mazowieckie",
			"vaccines": null,
			"diagnosis": false,
			"full_name": "Jan Kowalski",
			"is_delete": 0,
			"last_name": "Kowalski",
			"medicines": false,
			"parent_id": null,
			"surgeries": false,
			"birth_date": null,
			"disability": false,
			"first_name": "Jan",
			"house_number": "5",
			"maladjustment": null,
			"owner_user_id": "cl12345abcde",
			"street_number": "5A",
			"medicines_dose": null,
			"medicines_name": null,
			"surgeries_date": null,
			"medicines_cause": null,
			"surgeries_cause": null,
			"ag_state_version": 1,
			"illness_symptoms": null,
			"alergies_symptoms": null,
			"other_information": null,
			"diagnosis_symptoms": null,
			"illness_description": null,
			"alergies_description": null,
			"diagnosis_description": null,
			"surgeries_desctiption": null,
			"disability_description": null,
			"maladjustment_description": null
		},
		"payment_due_date": "2025-06-15",
		"advance_payment_due_date": "2025-05-15",
		"payment_status": "UNPAID",
		"advance_payment_status": "NOT_PAID",
		"advance_payment_price": 300,
		"start_date": "2025-07-01",
		"end_date": "2025-07-15",
		"base_price_per_person": 1200,
		"product_name": "Kolonie 2025",
		"trip_name": "Kolonie w górach",
		"user_name": "rodzic@example.com",
		"company_name": "Górska Przygoda",
		"type": "BOOKING",
		"rejection_reason": null,
		"rejection_description": null,
		"original_total_price": 1200,
		"original_advance_payment": 300,
		"trip_length_days": 14,
		"participants_count": 1,
		"min_age": 7,
		"max_age": 18,
		"destination_province": "małopolskie",
		"destination_description": "Górska lokalizacja",
		"optional_trips": [],
		"inquiry_description": "",
		"month": "07",
		"departure_date": "2025-07-01",
		"departure_time": "08:00",
		"departure_address": "Dworzec PKP, Warszawa",
		"departure_remarks": "Zbiórka 30 minut przed odjazdem.",
		"return_date": "2025-07-15",
		"return_time": "18:00",
		"return_address": "Dworzec PKP, Warszawa",
		"return_remarks": "Powrót bezpośredni.",
		"free_places_count": 9,
		"transport_type": "autokar",
		"transport_vehicle": "Mercedes-Benz Tourismo",
		"transport_price_per_person": 50,
		"accommodation_place_id": "acc_001",
		"accommodation_price_per_person": 100,
		"places": [
			"Room 1"
		],
		"inquiry_id": "inq_001",
		"quotation_id": "quote_001",
		"departure_place": "Warszawa Centralna",
		"payment_mode": "online",
		"product_type": "kolonie",
		"customer_phone": "123456789",
		"customer_email": "rodzic@example.com",
		"initial_payment_amount": 300,
		"paid_amount": 300,
		"updated_at": "2025-01-02T10:00:00.000Z",
		"departure_place_price_per_pax": 10,
		"departure_place_price_total": 10,
		"advance_paid_at": "2025-01-02T10:05:00.000Z",
		"fully_paid_at": null,
		"payments": [
			{
				"id": "pay_001",
				"amount": 300,
				"date": "2025-01-02T10:05:00.000Z",
				"method": "card"
			}
		],
		"liveness_status": "ACTIVE",
		"currency": "PLN",
		"is_fee_paid": false,
		"promo_code_id": null,
		"influencer_name": null,
		"trip": null,
		"product": null,
		"company": null,
		"type_label": "Rezerwacja",
		"status_label": "Zaliczka Opłacona"
	},
	{
		"id": "book_321006",
		"status": "CREATED",
		"user_id": "cl67890fghij",
		"trip_id": "trip_0002",
		"product_id": "IN_ABC123XYZ",
		"company_id": "company_0002",
		"participants": [
			{
				"id": "kid_0002",
				"city": "Gdańsk",
				"type": "KID",
				"email": null,
				"pesel": "98765432109",
				"phone": null,
				"street": "Ulica Morska",
				"illness": false,
				"alergies": false,
				"postcode": "80-001",
				"province": "pomorskie",
				"vaccines": [],
				"diagnosis": false,
				"full_name": "Anna Nowak",
				"is_delete": 0,
				"last_name": "Nowak",
				"medicines": false,
				"parent_id": null,
				"surgeries": false,
				"birth_date": "2015-06-15",
				"disability": false,
				"first_name": "Anna",
				"house_number": "20",
				"maladjustment": false,
				"owner_user_id": "cl67890fghij",
				"street_number": "20B",
				"medicines_dose": null,
				"medicines_name": null,
				"surgeries_date": null,
				"medicines_cause": null,
				"surgeries_cause": null,
				"ag_state_version": 1,
				"illness_symptoms": null,
				"alergies_symptoms": null,
				"other_information": null,
				"diagnosis_symptoms": null,
				"illness_description": null,
				"alergies_description": null,
				"diagnosis_description": null,
				"surgeries_desctiption": null,
				"disability_description": null,
				"maladjustment_description": null
			}
		],
		"created_at": "2025-02-01T10:30:00.000Z",
		"total_price": 1500,
		"payable_price": 1500,
		"discount_amount": null,
		"deleted_at": null,
		"ag_state_version": 1,
		"trip_data": {
			"id": "trip_0002",
			"name": "Obóz żeglarski na Mazurach",
			"status": "ACTIVE",
			"advance": 400,
			"company": {
				"id": "company_0002",
				"name": "MazuryCamp"
			},
			"max_age": 18,
			"min_age": 10,
			"product": {
				"id": "PR_0002",
				"name": "Obóz Żeglarski 2025",
				"type": "kolonie"
			},
			"bookings": [],
			"end_date": "2025-07-22",
			"max_count": 12,
			"min_count": 1,
			"company_id": "company_0002",
			"created_at": "2025-01-01T10:00:00.000Z",
			"full_price": 1500,
			"is_deleted": false,
			"product_id": "PR_0002",
			"start_date": "2025-07-10",
			"archived_at": null,
			"is_archived": false,
			"product_type": "kolonie",
			"available_spots": null,
			"ag_state_version": 1,
			"reservation_price": null,
			"advance_conditions": null,
			"reservation_min_days": null,
			"discounts_description": null,
			"full_price_conditions": null
		},
		"product_data": {
			"id": "PR_0002",
			"name": "Obóz Żeglarski 2025",
			"type": "kolonie",
			"files": null,
			"media": null,
			"trips": [],
			"status": "ACTIVE",
			"company": {
				"id": "company_0002",
				"name": "MazuryCamp",
				"fc_website_url": null,
				"logo_image_url": null
			},
			"max_age": null,
			"min_age": null,
			"location": {
				"city": "",
				"street": "",
				"province": "",
				"post_code": "",
				"room_number": "",
				"house_number": ""
			},
			"food_type": null,
			"is_delete": false,
			"trip_type": null,
			"attributes": null,
			"company_id": "company_0002",
			"created_at": "2025-01-01T10:00:00.000Z",
			"food_vegan": null,
			"is_archive": false,
			"main_photo": {
				"id": "photo_0002",
				"url": "http://example.com/photo2.jpg",
				"width": 1700,
				"height": 1134,
				"provider": "cloudinary",
				"providerData": {}
			},
			"archived_at": null,
			"description": "Żeglarska przygoda 2025",
			"location_id": null,
			"country_code": "PL",
			"country_name": "Polska",
			"pickup_route": null,
			"published_at": null,
			"admin_comment": null,
			"category_code": null,
			"file_sections": null,
			"location_name": null,
			"transport_type": null,
			"food_vegetarian": null,
			"transport_route": null,
			"ag_state_version": 1,
			"food_description": null,
			"subcategory_code": null,
			"admin_approved_at": null,
			"transport_vehicle": null,
			"additional_info_text": null,
			"conditions_text_long": null,
			"schedule_description": null,
			"amenities_description": null,
			"conditions_text_short": null,
			"insurance_description": null,
			"transport_description": null,
			"admin_show_on_home_page": null,
			"participation_conditions": null,
			"participation_description": null,
			"admin_promote_on_home_page": null
		},
		"parent": {
			"id": "parent_0002",
			"city": "Gdańsk",
			"type": "PARENT",
			"email": "parent2@example.com",
			"pesel": null,
			"phone": "987654321",
			"street": "Ulica Morska",
			"illness": false,
			"alergies": false,
			"postcode": "80-001",
			"province": "pomorskie",
			"vaccines": null,
			"diagnosis": false,
			"full_name": "Tomasz Nowak",
			"is_delete": 0,
			"last_name": "Nowak",
			"medicines": false,
			"parent_id": null,
			"surgeries": false,
			"birth_date": null,
			"disability": false,
			"first_name": "Tomasz",
			"house_number": "20",
			"maladjustment": null,
			"owner_user_id": "cl67890fghij",
			"street_number": "20B",
			"medicines_dose": null,
			"medicines_name": null,
			"surgeries_date": null,
			"medicines_cause": null,
			"surgeries_cause": null,
			"ag_state_version": 1,
			"illness_symptoms": null,
			"alergies_symptoms": null,
			"other_information": null,
			"diagnosis_symptoms": null,
			"illness_description": null,
			"alergies_description": null,
			"diagnosis_description": null,
			"surgeries_desctiption": null,
			"disability_description": null,
			"maladjustment_description": null
		},
		"payment_due_date": "2025-07-01",
		"advance_payment_due_date": "2025-06-15",
		"payment_status": "FAILED",
		"advance_payment_status": "NOT_PAID",
		"advance_payment_price": 400,
		"start_date": "2025-07-10",
		"end_date": "2025-07-22",
		"base_price_per_person": 1500,
		"product_name": "Obóz Żeglarski 2025",
		"trip_name": "Obóz żeglarski na Mazurach",
		"user_name": "parent2@example.com",
		"company_name": "MazuryCamp",
		"type": "BOOKING",
		"rejection_reason": null,
		"rejection_description": null,
		"original_total_price": 1500,
		"original_advance_payment": 400,
		"trip_length_days": null,
		"participants_count": 1,
		"min_age": null,
		"max_age": null,
		"destination_province": null,
		"destination_description": null,
		"optional_trips": null,
		"inquiry_description": null,
		"month": null,
		"departure_date": null,
		"departure_time": null,
		"departure_address": null,
		"departure_remarks": null,
		"return_date": null,
		"return_time": null,
		"return_address": null,
		"return_remarks": null,
		"free_places_count": null,
		"transport_type": null,
		"transport_vehicle": null,
		"transport_price_per_person": null,
		"accommodation_place_id": null,
		"accommodation_price_per_person": null,
		"places": null,
		"inquiry_id": null,
		"quotation_id": null,
		"departure_place": null,
		"payment_mode": null,
		"product_type": null,
		"customer_phone": null,
		"customer_email": null,
		"initial_payment_amount": null,
		"paid_amount": null,
		"updated_at": null,
		"departure_place_price_per_pax": null,
		"departure_place_price_total": null,
		"advance_paid_at": null,
		"fully_paid_at": null,
		"payments": null,
		"liveness_status": "ACTIVE",
		"currency": "PLN",
		"is_fee_paid": false,
		"promo_code_id": null,
		"influencer_name": null,
		"trip": null,
		"product": null,
		"company": null,
		"type_label": "Rezerwacja",
		"status_label": "Oczekuje na zaliczkę"
	},
	{
		"id": "book_032102",
		"status": "ADVANCE_PAID",
		"user_id": "cl12345abcde",
		"trip_id": "trip_0001",
		"product_id": "IN_ABC123XYZ",
		"company_id": "company_0001",
		"participants": [
			{
				"id": "kid_0001",
				"city": "Warszawa",
				"type": "KID",
				"email": null,
				"pesel": "12345678901",
				"phone": null,
				"street": "Ulica ABC",
				"illness": false,
				"alergies": false,
				"postcode": "00-001",
				"province": "mazowieckie",
				"vaccines": [],
				"diagnosis": false,
				"full_name": "Adam Kowalski",
				"is_delete": 0,
				"last_name": "Kowalski",
				"medicines": false,
				"parent_id": null,
				"surgeries": false,
				"birth_date": "2020-01-01",
				"disability": false,
				"first_name": "Adam",
				"house_number": "10",
				"maladjustment": false,
				"owner_user_id": "cl12345abcde",
				"street_number": "5",
				"medicines_dose": null,
				"medicines_name": null,
				"surgeries_date": null,
				"medicines_cause": null,
				"surgeries_cause": null,
				"ag_state_version": 1,
				"illness_symptoms": null,
				"alergies_symptoms": null,
				"other_information": null,
				"diagnosis_symptoms": null,
				"illness_description": null,
				"alergies_description": null,
				"diagnosis_description": null,
				"surgeries_desctiption": null,
				"disability_description": null,
				"maladjustment_description": null
			},
			{
				"id": "kid_0001",
				"city": "Warszawa",
				"type": "KID",
				"email": null,
				"pesel": "12345678901",
				"phone": null,
				"street": "Ulica ABC",
				"illness": false,
				"alergies": false,
				"postcode": "00-001",
				"province": "mazowieckie",
				"vaccines": [],
				"diagnosis": false,
				"full_name": "Adam Kowalski",
				"is_delete": 0,
				"last_name": "Kowalski",
				"medicines": false,
				"parent_id": null,
				"surgeries": false,
				"birth_date": "2020-01-01",
				"disability": false,
				"first_name": "Adam",
				"house_number": "10",
				"maladjustment": false,
				"owner_user_id": "cl12345abcde",
				"street_number": "5",
				"medicines_dose": null,
				"medicines_name": null,
				"surgeries_date": null,
				"medicines_cause": null,
				"surgeries_cause": null,
				"ag_state_version": 1,
				"illness_symptoms": null,
				"alergies_symptoms": null,
				"other_information": null,
				"diagnosis_symptoms": null,
				"illness_description": null,
				"alergies_description": null,
				"diagnosis_description": null,
				"surgeries_desctiption": null,
				"disability_description": null,
				"maladjustment_description": null
			},
			{
				"id": "kid_0001",
				"city": "Warszawa",
				"type": "KID",
				"email": null,
				"pesel": "12345678901",
				"phone": null,
				"street": "Ulica ABC",
				"illness": false,
				"alergies": false,
				"postcode": "00-001",
				"province": "mazowieckie",
				"vaccines": [],
				"diagnosis": false,
				"full_name": "Adam Kowalski",
				"is_delete": 0,
				"last_name": "Kowalski",
				"medicines": false,
				"parent_id": null,
				"surgeries": false,
				"birth_date": "2020-01-01",
				"disability": false,
				"first_name": "Adam",
				"house_number": "10",
				"maladjustment": false,
				"owner_user_id": "cl12345abcde",
				"street_number": "5",
				"medicines_dose": null,
				"medicines_name": null,
				"surgeries_date": null,
				"medicines_cause": null,
				"surgeries_cause": null,
				"ag_state_version": 1,
				"illness_symptoms": null,
				"alergies_symptoms": null,
				"other_information": null,
				"diagnosis_symptoms": null,
				"illness_description": null,
				"alergies_description": null,
				"diagnosis_description": null,
				"surgeries_desctiption": null,
				"disability_description": null,
				"maladjustment_description": null
			},
			{
				"id": "kid_0001",
				"city": "Warszawa",
				"type": "KID",
				"email": null,
				"pesel": "12345678901",
				"phone": null,
				"street": "Ulica ABC",
				"illness": false,
				"alergies": false,
				"postcode": "00-001",
				"province": "mazowieckie",
				"vaccines": [],
				"diagnosis": false,
				"full_name": "Adam Kowalski",
				"is_delete": 0,
				"last_name": "Kowalski",
				"medicines": false,
				"parent_id": null,
				"surgeries": false,
				"birth_date": "2020-01-01",
				"disability": false,
				"first_name": "Adam",
				"house_number": "10",
				"maladjustment": false,
				"owner_user_id": "cl12345abcde",
				"street_number": "5",
				"medicines_dose": null,
				"medicines_name": null,
				"surgeries_date": null,
				"medicines_cause": null,
				"surgeries_cause": null,
				"ag_state_version": 1,
				"illness_symptoms": null,
				"alergies_symptoms": null,
				"other_information": null,
				"diagnosis_symptoms": null,
				"illness_description": null,
				"alergies_description": null,
				"diagnosis_description": null,
				"surgeries_desctiption": null,
				"disability_description": null,
				"maladjustment_description": null
			}
		],
		"created_at": "2025-01-01T09:00:00.000Z",
		"total_price": 1200,
		"payable_price": 1200,
		"discount_amount": null,
		"deleted_at": null,
		"ag_state_version": 3,
		"trip_data": {
			"id": "trip_0001",
			"name": "Kolonie w górach",
			"status": "ACTIVE",
			"advance": 300,
			"company": {
				"id": "company_0001",
				"name": "Górska Przygoda"
			},
			"max_age": 18,
			"min_age": 7,
			"product": {
				"id": "PR_0001",
				"name": "Kolonie 2025",
				"type": "kolonie"
			},
			"bookings": [],
			"end_date": "2025-07-15",
			"max_count": 10,
			"min_count": 1,
			"company_id": "company_0001",
			"created_at": "2024-12-01T09:00:00.000Z",
			"full_price": 1200,
			"is_deleted": false,
			"product_id": "PR_0001",
			"start_date": "2025-07-01",
			"archived_at": null,
			"is_archived": false,
			"product_type": "kolonie",
			"available_spots": null,
			"ag_state_version": 1,
			"reservation_price": null,
			"advance_conditions": null,
			"reservation_min_days": null,
			"discounts_description": null,
			"full_price_conditions": null
		},
		"product_data": {
			"id": "IN_H1QHK1RSOD",
			"name": "Kolonie 2025",
			"type": "kolonie",
			"files": null,
			"media": null,
			"trips": [],
			"status": "ACTIVE",
			"company": {
				"id": "company_0001",
				"name": "Górska Przygoda",
				"fc_website_url": null,
				"logo_image_url": null
			},
			"max_age": null,
			"min_age": null,
			"location": {
				"city": "",
				"street": "",
				"province": "",
				"post_code": "",
				"room_number": "",
				"house_number": ""
			},
			"food_type": null,
			"is_delete": false,
			"trip_type": null,
			"attributes": null,
			"company_id": "company_0001",
			"created_at": "2024-12-01T09:00:00.000Z",
			"food_vegan": null,
			"is_archive": false,
			"main_photo": {
				"id": "photo_0001",
				"url": "http://example.com/photo1.jpg",
				"width": 1700,
				"height": 1134,
				"provider": "cloudinary",
				"providerData": {}
			},
			"archived_at": null,
			"description": "Kolonie w górach 2025",
			"location_id": null,
			"country_code": "PL",
			"country_name": "Polska",
			"pickup_route": null,
			"published_at": null,
			"admin_comment": null,
			"category_code": null,
			"file_sections": null,
			"location_name": null,
			"transport_type": null,
			"food_vegetarian": null,
			"transport_route": null,
			"ag_state_version": 1,
			"food_description": null,
			"subcategory_code": null,
			"admin_approved_at": null,
			"transport_vehicle": null,
			"additional_info_text": null,
			"conditions_text_long": null,
			"schedule_description": null,
			"amenities_description": null,
			"conditions_text_short": null,
			"insurance_description": null,
			"transport_description": null,
			"admin_show_on_home_page": null,
			"participation_conditions": null,
			"participation_description": null,
			"admin_promote_on_home_page": null
		},
		"parent": {
			"id": "parent_0001",
			"city": "Warszawa",
			"type": "PARENT",
			"email": "rodzic@example.com",
			"pesel": null,
			"phone": "123456789",
			"street": "Ulica Nowa",
			"illness": false,
			"alergies": false,
			"postcode": "00-001",
			"province": "mazowieckie",
			"vaccines": null,
			"diagnosis": false,
			"full_name": "Jan Kowalski",
			"is_delete": 0,
			"last_name": "Kowalski",
			"medicines": false,
			"parent_id": null,
			"surgeries": false,
			"birth_date": null,
			"disability": false,
			"first_name": "Jan",
			"house_number": "5",
			"maladjustment": null,
			"owner_user_id": "cl12345abcde",
			"street_number": "5A",
			"medicines_dose": null,
			"medicines_name": null,
			"surgeries_date": null,
			"medicines_cause": null,
			"surgeries_cause": null,
			"ag_state_version": 1,
			"illness_symptoms": null,
			"alergies_symptoms": null,
			"other_information": null,
			"diagnosis_symptoms": null,
			"illness_description": null,
			"alergies_description": null,
			"diagnosis_description": null,
			"surgeries_desctiption": null,
			"disability_description": null,
			"maladjustment_description": null
		},
		"payment_due_date": "2025-06-15",
		"advance_payment_due_date": "2025-05-15",
		"payment_status": "PAID",
		"advance_payment_status": "NOT_PAID",
		"advance_payment_price": 300,
		"start_date": "2025-07-01",
		"end_date": "2025-07-15",
		"base_price_per_person": 1200,
		"product_name": "Kolonie 2025",
		"trip_name": "Kolonie w górach",
		"user_name": "rodzic@example.com",
		"company_name": "Górska Przygoda",
		"type": "BOOKING",
		"rejection_reason": null,
		"rejection_description": null,
		"original_total_price": 1200,
		"original_advance_payment": 300,
		"trip_length_days": null,
		"participants_count": 1,
		"min_age": null,
		"max_age": null,
		"destination_province": null,
		"destination_description": null,
		"optional_trips": null,
		"inquiry_description": null,
		"month": null,
		"departure_date": null,
		"departure_time": null,
		"departure_address": null,
		"departure_remarks": null,
		"return_date": null,
		"return_time": null,
		"return_address": null,
		"return_remarks": null,
		"free_places_count": null,
		"transport_type": null,
		"transport_vehicle": null,
		"transport_price_per_person": null,
		"accommodation_place_id": null,
		"accommodation_price_per_person": null,
		"places": null,
		"inquiry_id": null,
		"quotation_id": null,
		"departure_place": null,
		"payment_mode": null,
		"product_type": null,
		"customer_phone": null,
		"customer_email": null,
		"initial_payment_amount": null,
		"paid_amount": null,
		"updated_at": null,
		"departure_place_price_per_pax": null,
		"departure_place_price_total": null,
		"advance_paid_at": null,
		"fully_paid_at": null,
		"payments": null,
		"liveness_status": "ACTIVE",
		"currency": "PLN",
		"is_fee_paid": false,
		"promo_code_id": null,
		"influencer_name": null,
		"trip": null,
		"product": null,
		"company": null,
		"type_label": "Rezerwacja",
		"status_label": "Zaliczka Opłacona"
	},
	{
		"id": "fasd12",
		"status": "CREATED",
		"user_id": "cl67890fghij",
		"trip_id": "trip_0002",
		"product_id": "PR_0002",
		"company_id": "company_0002",
		"participants": [
			{
				"id": "kid_0002",
				"city": "Gdańsk",
				"type": "KID",
				"email": null,
				"pesel": "98765432109",
				"phone": null,
				"street": "Ulica Morska",
				"illness": false,
				"alergies": false,
				"postcode": "80-001",
				"province": "pomorskie",
				"vaccines": [],
				"diagnosis": false,
				"full_name": "Anna Nowak",
				"is_delete": 0,
				"last_name": "Nowak",
				"medicines": false,
				"parent_id": null,
				"surgeries": false,
				"birth_date": "2015-06-15",
				"disability": false,
				"first_name": "Anna",
				"house_number": "20",
				"maladjustment": false,
				"owner_user_id": "cl67890fghij",
				"street_number": "20B",
				"medicines_dose": null,
				"medicines_name": null,
				"surgeries_date": null,
				"medicines_cause": null,
				"surgeries_cause": null,
				"ag_state_version": 1,
				"illness_symptoms": null,
				"alergies_symptoms": null,
				"other_information": null,
				"diagnosis_symptoms": null,
				"illness_description": null,
				"alergies_description": null,
				"diagnosis_description": null,
				"surgeries_desctiption": null,
				"disability_description": null,
				"maladjustment_description": null
			}
		],
		"created_at": "2025-02-01T10:30:00.000Z",
		"total_price": 1500,
		"payable_price": 1500,
		"discount_amount": null,
		"deleted_at": null,
		"ag_state_version": 1,
		"trip_data": {
			"id": "trip_0002",
			"name": "Obóz żeglarski na Mazurach",
			"status": "ACTIVE",
			"advance": 400,
			"company": {
				"id": "company_0002",
				"name": "MazuryCamp"
			},
			"max_age": 18,
			"min_age": 10,
			"product": {
				"id": "PR_0002",
				"name": "Obóz Żeglarski 2025",
				"type": "kolonie"
			},
			"bookings": [],
			"end_date": "2025-07-22",
			"max_count": 12,
			"min_count": 1,
			"company_id": "company_0002",
			"created_at": "2025-01-01T10:00:00.000Z",
			"full_price": 1500,
			"is_deleted": false,
			"product_id": "PR_0002",
			"start_date": "2025-07-10",
			"archived_at": null,
			"is_archived": false,
			"product_type": "kolonie",
			"available_spots": null,
			"ag_state_version": 1,
			"reservation_price": null,
			"advance_conditions": null,
			"reservation_min_days": null,
			"discounts_description": null,
			"full_price_conditions": null
		},
		"product_data": {
			"id": "PR_0002",
			"name": "Obóz Żeglarski 2025",
			"type": "kolonie",
			"files": null,
			"media": null,
			"trips": [],
			"status": "ACTIVE",
			"company": {
				"id": "company_0002",
				"name": "MazuryCamp",
				"fc_website_url": null,
				"logo_image_url": null
			},
			"max_age": null,
			"min_age": null,
			"location": {
				"city": "",
				"street": "",
				"province": "",
				"post_code": "",
				"room_number": "",
				"house_number": ""
			},
			"food_type": null,
			"is_delete": false,
			"trip_type": null,
			"attributes": null,
			"company_id": "company_0002",
			"created_at": "2025-01-01T10:00:00.000Z",
			"food_vegan": null,
			"is_archive": false,
			"main_photo": {
				"id": "photo_0002",
				"url": "http://example.com/photo2.jpg",
				"width": 1700,
				"height": 1134,
				"provider": "cloudinary",
				"providerData": {}
			},
			"archived_at": null,
			"description": "Żeglarska przygoda 2025",
			"location_id": null,
			"country_code": "PL",
			"country_name": "Polska",
			"pickup_route": null,
			"published_at": null,
			"admin_comment": null,
			"category_code": null,
			"file_sections": null,
			"location_name": null,
			"transport_type": null,
			"food_vegetarian": null,
			"transport_route": null,
			"ag_state_version": 1,
			"food_description": null,
			"subcategory_code": null,
			"admin_approved_at": null,
			"transport_vehicle": null,
			"additional_info_text": null,
			"conditions_text_long": null,
			"schedule_description": null,
			"amenities_description": null,
			"conditions_text_short": null,
			"insurance_description": null,
			"transport_description": null,
			"admin_show_on_home_page": null,
			"participation_conditions": null,
			"participation_description": null,
			"admin_promote_on_home_page": null
		},
		"parent": {
			"id": "parent_0002",
			"city": "Gdańsk",
			"type": "PARENT",
			"email": "parent2@example.com",
			"pesel": null,
			"phone": "987654321",
			"street": "Ulica Morska",
			"illness": false,
			"alergies": false,
			"postcode": "80-001",
			"province": "pomorskie",
			"vaccines": null,
			"diagnosis": false,
			"full_name": "Tomasz Nowak",
			"is_delete": 0,
			"last_name": "Nowak",
			"medicines": false,
			"parent_id": null,
			"surgeries": false,
			"birth_date": null,
			"disability": false,
			"first_name": "Tomasz",
			"house_number": "20",
			"maladjustment": null,
			"owner_user_id": "cl67890fghij",
			"street_number": "20B",
			"medicines_dose": null,
			"medicines_name": null,
			"surgeries_date": null,
			"medicines_cause": null,
			"surgeries_cause": null,
			"ag_state_version": 1,
			"illness_symptoms": null,
			"alergies_symptoms": null,
			"other_information": null,
			"diagnosis_symptoms": null,
			"illness_description": null,
			"alergies_description": null,
			"diagnosis_description": null,
			"surgeries_desctiption": null,
			"disability_description": null,
			"maladjustment_description": null
		},
		"payment_due_date": "2025-07-01",
		"advance_payment_due_date": "2025-06-15",
		"payment_status": "REFUNDED",
		"advance_payment_status": "NOT_PAID",
		"advance_payment_price": 400,
		"start_date": "2025-07-10",
		"end_date": "2025-07-22",
		"base_price_per_person": 1500,
		"product_name": "Obóz Żeglarski 2025",
		"trip_name": "Obóz żeglarski na Mazurach",
		"user_name": "parent2@example.com",
		"company_name": "MazuryCamp",
		"type": "BOOKING",
		"rejection_reason": null,
		"rejection_description": null,
		"original_total_price": 1500,
		"original_advance_payment": 400,
		"trip_length_days": null,
		"participants_count": 1,
		"min_age": null,
		"max_age": null,
		"destination_province": null,
		"destination_description": null,
		"optional_trips": null,
		"inquiry_description": null,
		"month": null,
		"departure_date": null,
		"departure_time": null,
		"departure_address": null,
		"departure_remarks": null,
		"return_date": null,
		"return_time": null,
		"return_address": null,
		"return_remarks": null,
		"free_places_count": null,
		"transport_type": null,
		"transport_vehicle": null,
		"transport_price_per_person": null,
		"accommodation_place_id": null,
		"accommodation_price_per_person": null,
		"places": null,
		"inquiry_id": null,
		"quotation_id": null,
		"departure_place": null,
		"payment_mode": null,
		"product_type": null,
		"customer_phone": null,
		"customer_email": null,
		"initial_payment_amount": null,
		"paid_amount": null,
		"updated_at": null,
		"departure_place_price_per_pax": null,
		"departure_place_price_total": null,
		"advance_paid_at": null,
		"fully_paid_at": null,
		"payments": null,
		"liveness_status": "ACTIVE",
		"currency": "PLN",
		"is_fee_paid": false,
		"promo_code_id": null,
		"influencer_name": null,
		"trip": null,
		"product": null,
		"company": null,
		"type_label": "Rezerwacja",
		"status_label": "Oczekuje na zaliczkę"
	},
	{
		"id": "book_012",
		"status": "ADVANCE_PAID",
		"user_id": "cl12345abcde",
		"trip_id": "trip_0001",
		"product_id": "IN_H1QHK1RSOD",
		"company_id": "company_0001",
		"participants": [
			{
				"id": "kid_0001",
				"city": "Warszawa",
				"type": "KID",
				"email": null,
				"pesel": "12345678901",
				"phone": null,
				"street": "Ulica ABC",
				"illness": false,
				"alergies": false,
				"postcode": "00-001",
				"province": "mazowieckie",
				"vaccines": [],
				"diagnosis": false,
				"full_name": "Adam Kowalski",
				"is_delete": 0,
				"last_name": "Kowalski",
				"medicines": false,
				"parent_id": null,
				"surgeries": false,
				"birth_date": "2020-01-01",
				"disability": false,
				"first_name": "Adam",
				"house_number": "10",
				"maladjustment": false,
				"owner_user_id": "cl12345abcde",
				"street_number": "5",
				"medicines_dose": null,
				"medicines_name": null,
				"surgeries_date": null,
				"medicines_cause": null,
				"surgeries_cause": null,
				"ag_state_version": 1,
				"illness_symptoms": null,
				"alergies_symptoms": null,
				"other_information": null,
				"diagnosis_symptoms": null,
				"illness_description": null,
				"alergies_description": null,
				"diagnosis_description": null,
				"surgeries_desctiption": null,
				"disability_description": null,
				"maladjustment_description": null
			}
		],
		"created_at": "2025-01-01T09:00:00.000Z",
		"total_price": 1200,
		"payable_price": 1200,
		"discount_amount": 0,
		"deleted_at": null,
		"ag_state_version": 3,
		"trip_data": {
			"id": "trip_0001",
			"name": "Kolonie w górach",
			"status": "ACTIVE",
			"advance": 300,
			"company": {
				"id": "company_0001",
				"name": "Górska Przygoda"
			},
			"max_age": 18,
			"min_age": 7,
			"product": {
				"id": "PR_0001",
				"name": "Kolonie 2025",
				"type": "kolonie"
			},
			"bookings": [],
			"end_date": "2025-07-15",
			"max_count": 10,
			"min_count": 1,
			"company_id": "company_0001",
			"created_at": "2024-12-01T09:00:00.000Z",
			"full_price": 1200,
			"is_deleted": false,
			"product_id": "PR_0001",
			"start_date": "2025-07-01",
			"archived_at": null,
			"is_archived": false,
			"product_type": "kolonie",
			"available_spots": 9,
			"ag_state_version": 1,
			"reservation_price": 1200,
			"advance_conditions": null,
			"reservation_min_days": null,
			"discounts_description": null,
			"full_price_conditions": null
		},
		"product_data": {
			"id": "IN_H1QHK1RSOD",
			"name": "Kolonie 2025",
			"type": "kolonie",
			"files": null,
			"media": null,
			"trips": [],
			"status": "ACTIVE",
			"company": {
				"id": "company_0001",
				"name": "Górska Przygoda",
				"fc_website_url": null,
				"logo_image_url": null
			},
			"max_age": 18,
			"min_age": 7,
			"location": {
				"city": "Zakopane",
				"street": "Ul. Górska",
				"province": "małopolskie",
				"post_code": "34-500",
				"room_number": "101",
				"house_number": "15"
			},
			"food_type": null,
			"is_delete": false,
			"trip_type": null,
			"attributes": null,
			"company_id": "company_0001",
			"created_at": "2024-12-01T09:00:00.000Z",
			"food_vegan": null,
			"is_archive": false,
			"main_photo": {
				"id": "photo_0001",
				"url": "http://example.com/photo1.jpg",
				"width": 1700,
				"height": 1134,
				"provider": "cloudinary",
				"providerData": {}
			},
			"archived_at": null,
			"description": "Kolonie w górach 2025",
			"location_id": null,
			"country_code": "PL",
			"country_name": "Polska",
			"pickup_route": null,
			"published_at": null,
			"admin_comment": null,
			"category_code": null,
			"file_sections": null,
			"location_name": null,
			"transport_type": "autokar",
			"food_vegetarian": null,
			"transport_route": null,
			"ag_state_version": 1,
			"food_description": null,
			"subcategory_code": null,
			"admin_approved_at": null,
			"transport_vehicle": "Mercedes-Benz Tourismo",
			"additional_info_text": null,
			"conditions_text_long": null,
			"schedule_description": null,
			"amenities_description": null,
			"conditions_text_short": null,
			"insurance_description": null,
			"transport_description": null,
			"admin_show_on_home_page": null,
			"participation_conditions": null,
			"participation_description": null,
			"admin_promote_on_home_page": null
		},
		"parent": {
			"id": "parent_0001",
			"city": "Warszawa",
			"type": "PARENT",
			"email": "rodzic@example.com",
			"pesel": null,
			"phone": "123456789",
			"street": "Ulica Nowa",
			"illness": false,
			"alergies": false,
			"postcode": "00-001",
			"province": "mazowieckie",
			"vaccines": null,
			"diagnosis": false,
			"full_name": "Jan Kowalski",
			"is_delete": 0,
			"last_name": "Kowalski",
			"medicines": false,
			"parent_id": null,
			"surgeries": false,
			"birth_date": null,
			"disability": false,
			"first_name": "Jan",
			"house_number": "5",
			"maladjustment": null,
			"owner_user_id": "cl12345abcde",
			"street_number": "5A",
			"medicines_dose": null,
			"medicines_name": null,
			"surgeries_date": null,
			"medicines_cause": null,
			"surgeries_cause": null,
			"ag_state_version": 1,
			"illness_symptoms": null,
			"alergies_symptoms": null,
			"other_information": null,
			"diagnosis_symptoms": null,
			"illness_description": null,
			"alergies_description": null,
			"diagnosis_description": null,
			"surgeries_desctiption": null,
			"disability_description": null,
			"maladjustment_description": null
		},
		"payment_due_date": "2025-06-15",
		"advance_payment_due_date": "2025-05-15",
		"payment_status": "UNPAID",
		"advance_payment_status": "NOT_PAID",
		"advance_payment_price": 300,
		"start_date": "2025-07-01",
		"end_date": "2025-07-15",
		"base_price_per_person": 1200,
		"product_name": "Kolonie 2025",
		"trip_name": "Kolonie w górach",
		"user_name": "rodzic@example.com",
		"company_name": "Górska Przygoda",
		"type": "BOOKING",
		"rejection_reason": null,
		"rejection_description": null,
		"original_total_price": 1200,
		"original_advance_payment": 300,
		"trip_length_days": 14,
		"participants_count": 1,
		"min_age": 7,
		"max_age": 18,
		"destination_province": "małopolskie",
		"destination_description": "Górska lokalizacja",
		"optional_trips": [],
		"inquiry_description": "",
		"month": "07",
		"departure_date": "2025-07-01",
		"departure_time": "08:00",
		"departure_address": "Dworzec PKP, Warszawa",
		"departure_remarks": "Zbiórka 30 minut przed odjazdem.",
		"return_date": "2025-07-15",
		"return_time": "18:00",
		"return_address": "Dworzec PKP, Warszawa",
		"return_remarks": "Powrót bezpośredni.",
		"free_places_count": 9,
		"transport_type": "autokar",
		"transport_vehicle": "Mercedes-Benz Tourismo",
		"transport_price_per_person": 50,
		"accommodation_place_id": "acc_001",
		"accommodation_price_per_person": 100,
		"places": [
			"Room 1"
		],
		"inquiry_id": "inq_001",
		"quotation_id": "quote_001",
		"departure_place": "Warszawa Centralna",
		"payment_mode": "online",
		"product_type": "kolonie",
		"customer_phone": "123456789",
		"customer_email": "rodzic@example.com",
		"initial_payment_amount": 300,
		"paid_amount": 300,
		"updated_at": "2025-01-02T10:00:00.000Z",
		"departure_place_price_per_pax": 10,
		"departure_place_price_total": 10,
		"advance_paid_at": "2025-01-02T10:05:00.000Z",
		"fully_paid_at": null,
		"payments": [
			{
				"id": "pay_001",
				"amount": 300,
				"date": "2025-01-02T10:05:00.000Z",
				"method": "card"
			}
		],
		"liveness_status": "ACTIVE",
		"currency": "PLN",
		"is_fee_paid": false,
		"promo_code_id": null,
		"influencer_name": null,
		"trip": null,
		"product": null,
		"company": null,
		"type_label": "Rezerwacja",
		"status_label": "Zaliczka Opłacona"
	},
	{
		"id": "32212",
		"status": "CREATED",
		"user_id": "cl67890fghij",
		"trip_id": "trip_0002",
		"product_id": "IN_H1QHK1RSOD",
		"company_id": "company_0002",
		"participants": [
			{
				"id": "kid_0002",
				"city": "Gdańsk",
				"type": "KID",
				"email": null,
				"pesel": "98765432109",
				"phone": null,
				"street": "Ulica Morska",
				"illness": false,
				"alergies": false,
				"postcode": "80-001",
				"province": "pomorskie",
				"vaccines": [],
				"diagnosis": false,
				"full_name": "Anna Nowak",
				"is_delete": 0,
				"last_name": "Nowak",
				"medicines": false,
				"parent_id": null,
				"surgeries": false,
				"birth_date": "2015-06-15",
				"disability": false,
				"first_name": "Anna",
				"house_number": "20",
				"maladjustment": false,
				"owner_user_id": "cl67890fghij",
				"street_number": "20B",
				"medicines_dose": null,
				"medicines_name": null,
				"surgeries_date": null,
				"medicines_cause": null,
				"surgeries_cause": null,
				"ag_state_version": 1,
				"illness_symptoms": null,
				"alergies_symptoms": null,
				"other_information": null,
				"diagnosis_symptoms": null,
				"illness_description": null,
				"alergies_description": null,
				"diagnosis_description": null,
				"surgeries_desctiption": null,
				"disability_description": null,
				"maladjustment_description": null
			}
		],
		"created_at": "2025-02-01T10:30:00.000Z",
		"total_price": 1500,
		"payable_price": 1500,
		"discount_amount": null,
		"deleted_at": null,
		"ag_state_version": 1,
		"trip_data": {
			"id": "trip_0002",
			"name": "Obóz żeglarski na Mazurach",
			"status": "ACTIVE",
			"advance": 400,
			"company": {
				"id": "company_0002",
				"name": "MazuryCamp"
			},
			"max_age": 18,
			"min_age": 10,
			"product": {
				"id": "PR_0002",
				"name": "Obóz Żeglarski 2025",
				"type": "kolonie"
			},
			"bookings": [],
			"end_date": "2025-07-22",
			"max_count": 12,
			"min_count": 1,
			"company_id": "company_0002",
			"created_at": "2025-01-01T10:00:00.000Z",
			"full_price": 1500,
			"is_deleted": false,
			"product_id": "PR_0002",
			"start_date": "2025-07-10",
			"archived_at": null,
			"is_archived": false,
			"product_type": "kolonie",
			"available_spots": null,
			"ag_state_version": 1,
			"reservation_price": null,
			"advance_conditions": null,
			"reservation_min_days": null,
			"discounts_description": null,
			"full_price_conditions": null
		},
		"product_data": {
			"id": "PR_0002",
			"name": "Obóz Żeglarski 2025",
			"type": "kolonie",
			"files": null,
			"media": null,
			"trips": [],
			"status": "ACTIVE",
			"company": {
				"id": "company_0002",
				"name": "MazuryCamp",
				"fc_website_url": null,
				"logo_image_url": null
			},
			"max_age": null,
			"min_age": null,
			"location": {
				"city": "",
				"street": "",
				"province": "",
				"post_code": "",
				"room_number": "",
				"house_number": ""
			},
			"food_type": null,
			"is_delete": false,
			"trip_type": null,
			"attributes": null,
			"company_id": "company_0002",
			"created_at": "2025-01-01T10:00:00.000Z",
			"food_vegan": null,
			"is_archive": false,
			"main_photo": {
				"id": "photo_0002",
				"url": "http://example.com/photo2.jpg",
				"width": 1700,
				"height": 1134,
				"provider": "cloudinary",
				"providerData": {}
			},
			"archived_at": null,
			"description": "Żeglarska przygoda 2025",
			"location_id": null,
			"country_code": "PL",
			"country_name": "Polska",
			"pickup_route": null,
			"published_at": null,
			"admin_comment": null,
			"category_code": null,
			"file_sections": null,
			"location_name": null,
			"transport_type": null,
			"food_vegetarian": null,
			"transport_route": null,
			"ag_state_version": 1,
			"food_description": null,
			"subcategory_code": null,
			"admin_approved_at": null,
			"transport_vehicle": null,
			"additional_info_text": null,
			"conditions_text_long": null,
			"schedule_description": null,
			"amenities_description": null,
			"conditions_text_short": null,
			"insurance_description": null,
			"transport_description": null,
			"admin_show_on_home_page": null,
			"participation_conditions": null,
			"participation_description": null,
			"admin_promote_on_home_page": null
		},
		"parent": {
			"id": "parent_0002",
			"city": "Gdańsk",
			"type": "PARENT",
			"email": "parent2@example.com",
			"pesel": null,
			"phone": "987654321",
			"street": "Ulica Morska",
			"illness": false,
			"alergies": false,
			"postcode": "80-001",
			"province": "pomorskie",
			"vaccines": null,
			"diagnosis": false,
			"full_name": "Tomasz Nowak",
			"is_delete": 0,
			"last_name": "Nowak",
			"medicines": false,
			"parent_id": null,
			"surgeries": false,
			"birth_date": null,
			"disability": false,
			"first_name": "Tomasz",
			"house_number": "20",
			"maladjustment": null,
			"owner_user_id": "cl67890fghij",
			"street_number": "20B",
			"medicines_dose": null,
			"medicines_name": null,
			"surgeries_date": null,
			"medicines_cause": null,
			"surgeries_cause": null,
			"ag_state_version": 1,
			"illness_symptoms": null,
			"alergies_symptoms": null,
			"other_information": null,
			"diagnosis_symptoms": null,
			"illness_description": null,
			"alergies_description": null,
			"diagnosis_description": null,
			"surgeries_desctiption": null,
			"disability_description": null,
			"maladjustment_description": null
		},
		"payment_due_date": "2025-07-01",
		"advance_payment_due_date": "2025-06-15",
		"payment_status": "FAILED",
		"advance_payment_status": "NOT_PAID",
		"advance_payment_price": 400,
		"start_date": "2025-07-10",
		"end_date": "2025-07-22",
		"base_price_per_person": 1500,
		"product_name": "Obóz Żeglarski 2025",
		"trip_name": "Obóz żeglarski na Mazurach",
		"user_name": "parent2@example.com",
		"company_name": "MazuryCamp",
		"type": "BOOKING",
		"rejection_reason": null,
		"rejection_description": null,
		"original_total_price": 1500,
		"original_advance_payment": 400,
		"trip_length_days": null,
		"participants_count": 1,
		"min_age": null,
		"max_age": null,
		"destination_province": null,
		"destination_description": null,
		"optional_trips": null,
		"inquiry_description": null,
		"month": null,
		"departure_date": null,
		"departure_time": null,
		"departure_address": null,
		"departure_remarks": null,
		"return_date": null,
		"return_time": null,
		"return_address": null,
		"return_remarks": null,
		"free_places_count": null,
		"transport_type": null,
		"transport_vehicle": null,
		"transport_price_per_person": null,
		"accommodation_place_id": null,
		"accommodation_price_per_person": null,
		"places": null,
		"inquiry_id": null,
		"quotation_id": null,
		"departure_place": null,
		"payment_mode": null,
		"product_type": null,
		"customer_phone": null,
		"customer_email": null,
		"initial_payment_amount": null,
		"paid_amount": null,
		"updated_at": null,
		"departure_place_price_per_pax": null,
		"departure_place_price_total": null,
		"advance_paid_at": null,
		"fully_paid_at": null,
		"payments": null,
		"liveness_status": "ACTIVE",
		"currency": "PLN",
		"is_fee_paid": false,
		"promo_code_id": null,
		"influencer_name": null,
		"trip": null,
		"product": null,
		"company": null,
		"type_label": "Rezerwacja",
		"status_label": "Oczekuje na zaliczkę"
	},
	{
		"id": "312",
		"status": "ADVANCE_PAID",
		"user_id": "cl12345abcde",
		"trip_id": "trip_0001",
		"product_id": "IN_H1QHK1RSOD",
		"company_id": "company_0001",
		"participants": [
			{
				"id": "kid_0001",
				"city": "Warszawa",
				"type": "KID",
				"email": null,
				"pesel": "12345678901",
				"phone": null,
				"street": "Ulica ABC",
				"illness": false,
				"alergies": false,
				"postcode": "00-001",
				"province": "mazowieckie",
				"vaccines": [],
				"diagnosis": false,
				"full_name": "Adam Kowalski",
				"is_delete": 0,
				"last_name": "Kowalski",
				"medicines": false,
				"parent_id": null,
				"surgeries": false,
				"birth_date": "2020-01-01",
				"disability": false,
				"first_name": "Adam",
				"house_number": "10",
				"maladjustment": false,
				"owner_user_id": "cl12345abcde",
				"street_number": "5",
				"medicines_dose": null,
				"medicines_name": null,
				"surgeries_date": null,
				"medicines_cause": null,
				"surgeries_cause": null,
				"ag_state_version": 1,
				"illness_symptoms": null,
				"alergies_symptoms": null,
				"other_information": null,
				"diagnosis_symptoms": null,
				"illness_description": null,
				"alergies_description": null,
				"diagnosis_description": null,
				"surgeries_desctiption": null,
				"disability_description": null,
				"maladjustment_description": null
			},
			{
				"id": "kid_0001",
				"city": "Warszawa",
				"type": "KID",
				"email": null,
				"pesel": "12345678901",
				"phone": null,
				"street": "Ulica ABC",
				"illness": false,
				"alergies": false,
				"postcode": "00-001",
				"province": "mazowieckie",
				"vaccines": [],
				"diagnosis": false,
				"full_name": "Adam Kowalski",
				"is_delete": 0,
				"last_name": "Kowalski",
				"medicines": false,
				"parent_id": null,
				"surgeries": false,
				"birth_date": "2020-01-01",
				"disability": false,
				"first_name": "Adam",
				"house_number": "10",
				"maladjustment": false,
				"owner_user_id": "cl12345abcde",
				"street_number": "5",
				"medicines_dose": null,
				"medicines_name": null,
				"surgeries_date": null,
				"medicines_cause": null,
				"surgeries_cause": null,
				"ag_state_version": 1,
				"illness_symptoms": null,
				"alergies_symptoms": null,
				"other_information": null,
				"diagnosis_symptoms": null,
				"illness_description": null,
				"alergies_description": null,
				"diagnosis_description": null,
				"surgeries_desctiption": null,
				"disability_description": null,
				"maladjustment_description": null
			},
			{
				"id": "kid_0001",
				"city": "Warszawa",
				"type": "KID",
				"email": null,
				"pesel": "12345678901",
				"phone": null,
				"street": "Ulica ABC",
				"illness": false,
				"alergies": false,
				"postcode": "00-001",
				"province": "mazowieckie",
				"vaccines": [],
				"diagnosis": false,
				"full_name": "Adam Kowalski",
				"is_delete": 0,
				"last_name": "Kowalski",
				"medicines": false,
				"parent_id": null,
				"surgeries": false,
				"birth_date": "2020-01-01",
				"disability": false,
				"first_name": "Adam",
				"house_number": "10",
				"maladjustment": false,
				"owner_user_id": "cl12345abcde",
				"street_number": "5",
				"medicines_dose": null,
				"medicines_name": null,
				"surgeries_date": null,
				"medicines_cause": null,
				"surgeries_cause": null,
				"ag_state_version": 1,
				"illness_symptoms": null,
				"alergies_symptoms": null,
				"other_information": null,
				"diagnosis_symptoms": null,
				"illness_description": null,
				"alergies_description": null,
				"diagnosis_description": null,
				"surgeries_desctiption": null,
				"disability_description": null,
				"maladjustment_description": null
			},
			{
				"id": "kid_0001",
				"city": "Warszawa",
				"type": "KID",
				"email": null,
				"pesel": "12345678901",
				"phone": null,
				"street": "Ulica ABC",
				"illness": false,
				"alergies": false,
				"postcode": "00-001",
				"province": "mazowieckie",
				"vaccines": [],
				"diagnosis": false,
				"full_name": "Adam Kowalski",
				"is_delete": 0,
				"last_name": "Kowalski",
				"medicines": false,
				"parent_id": null,
				"surgeries": false,
				"birth_date": "2020-01-01",
				"disability": false,
				"first_name": "Adam",
				"house_number": "10",
				"maladjustment": false,
				"owner_user_id": "cl12345abcde",
				"street_number": "5",
				"medicines_dose": null,
				"medicines_name": null,
				"surgeries_date": null,
				"medicines_cause": null,
				"surgeries_cause": null,
				"ag_state_version": 1,
				"illness_symptoms": null,
				"alergies_symptoms": null,
				"other_information": null,
				"diagnosis_symptoms": null,
				"illness_description": null,
				"alergies_description": null,
				"diagnosis_description": null,
				"surgeries_desctiption": null,
				"disability_description": null,
				"maladjustment_description": null
			}
		],
		"created_at": "2025-01-01T09:00:00.000Z",
		"total_price": 1200,
		"payable_price": 1200,
		"discount_amount": null,
		"deleted_at": null,
		"ag_state_version": 3,
		"trip_data": {
			"id": "trip_0001",
			"name": "Kolonie w górach",
			"status": "ACTIVE",
			"advance": 300,
			"company": {
				"id": "company_0001",
				"name": "Górska Przygoda"
			},
			"max_age": 18,
			"min_age": 7,
			"product": {
				"id": "PR_0001",
				"name": "Kolonie 2025",
				"type": "kolonie"
			},
			"bookings": [],
			"end_date": "2025-07-15",
			"max_count": 10,
			"min_count": 1,
			"company_id": "company_0001",
			"created_at": "2024-12-01T09:00:00.000Z",
			"full_price": 1200,
			"is_deleted": false,
			"product_id": "PR_0001",
			"start_date": "2025-07-01",
			"archived_at": null,
			"is_archived": false,
			"product_type": "kolonie",
			"available_spots": null,
			"ag_state_version": 1,
			"reservation_price": null,
			"advance_conditions": null,
			"reservation_min_days": null,
			"discounts_description": null,
			"full_price_conditions": null
		},
		"product_data": {
			"id": "IN_H1QHK1RSOD",
			"name": "Kolonie 2025",
			"type": "kolonie",
			"files": null,
			"media": null,
			"trips": [],
			"status": "ACTIVE",
			"company": {
				"id": "company_0001",
				"name": "Górska Przygoda",
				"fc_website_url": null,
				"logo_image_url": null
			},
			"max_age": null,
			"min_age": null,
			"location": {
				"city": "",
				"street": "",
				"province": "",
				"post_code": "",
				"room_number": "",
				"house_number": ""
			},
			"food_type": null,
			"is_delete": false,
			"trip_type": null,
			"attributes": null,
			"company_id": "company_0001",
			"created_at": "2024-12-01T09:00:00.000Z",
			"food_vegan": null,
			"is_archive": false,
			"main_photo": {
				"id": "photo_0001",
				"url": "http://example.com/photo1.jpg",
				"width": 1700,
				"height": 1134,
				"provider": "cloudinary",
				"providerData": {}
			},
			"archived_at": null,
			"description": "Kolonie w górach 2025",
			"location_id": null,
			"country_code": "PL",
			"country_name": "Polska",
			"pickup_route": null,
			"published_at": null,
			"admin_comment": null,
			"category_code": null,
			"file_sections": null,
			"location_name": null,
			"transport_type": null,
			"food_vegetarian": null,
			"transport_route": null,
			"ag_state_version": 1,
			"food_description": null,
			"subcategory_code": null,
			"admin_approved_at": null,
			"transport_vehicle": null,
			"additional_info_text": null,
			"conditions_text_long": null,
			"schedule_description": null,
			"amenities_description": null,
			"conditions_text_short": null,
			"insurance_description": null,
			"transport_description": null,
			"admin_show_on_home_page": null,
			"participation_conditions": null,
			"participation_description": null,
			"admin_promote_on_home_page": null
		},
		"parent": {
			"id": "parent_0001",
			"city": "Warszawa",
			"type": "PARENT",
			"email": "rodzic@example.com",
			"pesel": null,
			"phone": "123456789",
			"street": "Ulica Nowa",
			"illness": false,
			"alergies": false,
			"postcode": "00-001",
			"province": "mazowieckie",
			"vaccines": null,
			"diagnosis": false,
			"full_name": "Jan Kowalski",
			"is_delete": 0,
			"last_name": "Kowalski",
			"medicines": false,
			"parent_id": null,
			"surgeries": false,
			"birth_date": null,
			"disability": false,
			"first_name": "Jan",
			"house_number": "5",
			"maladjustment": null,
			"owner_user_id": "cl12345abcde",
			"street_number": "5A",
			"medicines_dose": null,
			"medicines_name": null,
			"surgeries_date": null,
			"medicines_cause": null,
			"surgeries_cause": null,
			"ag_state_version": 1,
			"illness_symptoms": null,
			"alergies_symptoms": null,
			"other_information": null,
			"diagnosis_symptoms": null,
			"illness_description": null,
			"alergies_description": null,
			"diagnosis_description": null,
			"surgeries_desctiption": null,
			"disability_description": null,
			"maladjustment_description": null
		},
		"payment_due_date": "2025-06-15",
		"advance_payment_due_date": "2025-05-15",
		"payment_status": "PAID",
		"advance_payment_status": "NOT_PAID",
		"advance_payment_price": 300,
		"start_date": "2025-07-01",
		"end_date": "2025-07-15",
		"base_price_per_person": 1200,
		"product_name": "Kolonie 2025",
		"trip_name": "Kolonie w górach",
		"user_name": "rodzic@example.com",
		"company_name": "Górska Przygoda",
		"type": "BOOKING",
		"rejection_reason": null,
		"rejection_description": null,
		"original_total_price": 1200,
		"original_advance_payment": 300,
		"trip_length_days": null,
		"participants_count": 1,
		"min_age": null,
		"max_age": null,
		"destination_province": null,
		"destination_description": null,
		"optional_trips": null,
		"inquiry_description": null,
		"month": null,
		"departure_date": null,
		"departure_time": null,
		"departure_address": null,
		"departure_remarks": null,
		"return_date": null,
		"return_time": null,
		"return_address": null,
		"return_remarks": null,
		"free_places_count": null,
		"transport_type": null,
		"transport_vehicle": null,
		"transport_price_per_person": null,
		"accommodation_place_id": null,
		"accommodation_price_per_person": null,
		"places": null,
		"inquiry_id": null,
		"quotation_id": null,
		"departure_place": null,
		"payment_mode": null,
		"product_type": null,
		"customer_phone": null,
		"customer_email": null,
		"initial_payment_amount": null,
		"paid_amount": null,
		"updated_at": null,
		"departure_place_price_per_pax": null,
		"departure_place_price_total": null,
		"advance_paid_at": null,
		"fully_paid_at": null,
		"payments": null,
		"liveness_status": "ACTIVE",
		"currency": "PLN",
		"is_fee_paid": false,
		"promo_code_id": null,
		"influencer_name": null,
		"trip": null,
		"product": null,
		"company": null,
		"type_label": "Rezerwacja",
		"status_label": "Zaliczka Opłacona"
	},
	{
		"id": "book_003",
		"status": "CREATED",
		"user_id": "cl67890fghij",
		"trip_id": "trip_0002",
		"product_id": "IN_H1QHK1RSOD",
		"company_id": "company_0002",
		"participants": [
			{
				"id": "kid_0002",
				"city": "Gdańsk",
				"type": "KID",
				"email": null,
				"pesel": "98765432109",
				"phone": null,
				"street": "Ulica Morska",
				"illness": false,
				"alergies": false,
				"postcode": "80-001",
				"province": "pomorskie",
				"vaccines": [],
				"diagnosis": false,
				"full_name": "Anna Nowak",
				"is_delete": 0,
				"last_name": "Nowak",
				"medicines": false,
				"parent_id": null,
				"surgeries": false,
				"birth_date": "2015-06-15",
				"disability": false,
				"first_name": "Anna",
				"house_number": "20",
				"maladjustment": false,
				"owner_user_id": "cl67890fghij",
				"street_number": "20B",
				"medicines_dose": null,
				"medicines_name": null,
				"surgeries_date": null,
				"medicines_cause": null,
				"surgeries_cause": null,
				"ag_state_version": 1,
				"illness_symptoms": null,
				"alergies_symptoms": null,
				"other_information": null,
				"diagnosis_symptoms": null,
				"illness_description": null,
				"alergies_description": null,
				"diagnosis_description": null,
				"surgeries_desctiption": null,
				"disability_description": null,
				"maladjustment_description": null
			}
		],
		"created_at": "2025-02-01T10:30:00.000Z",
		"total_price": 1500,
		"payable_price": 1500,
		"discount_amount": null,
		"deleted_at": null,
		"ag_state_version": 1,
		"trip_data": {
			"id": "trip_0002",
			"name": "Obóz żeglarski na Mazurach",
			"status": "ACTIVE",
			"advance": 400,
			"company": {
				"id": "company_0002",
				"name": "MazuryCamp"
			},
			"max_age": 18,
			"min_age": 10,
			"product": {
				"id": "PR_0002",
				"name": "Obóz Żeglarski 2025",
				"type": "kolonie"
			},
			"bookings": [],
			"end_date": "2025-07-22",
			"max_count": 12,
			"min_count": 1,
			"company_id": "company_0002",
			"created_at": "2025-01-01T10:00:00.000Z",
			"full_price": 1500,
			"is_deleted": false,
			"product_id": "PR_0002",
			"start_date": "2025-07-10",
			"archived_at": null,
			"is_archived": false,
			"product_type": "kolonie",
			"available_spots": null,
			"ag_state_version": 1,
			"reservation_price": null,
			"advance_conditions": null,
			"reservation_min_days": null,
			"discounts_description": null,
			"full_price_conditions": null
		},
		"product_data": {
			"id": "PR_0002",
			"name": "Obóz Żeglarski 2025",
			"type": "kolonie",
			"files": null,
			"media": null,
			"trips": [],
			"status": "ACTIVE",
			"company": {
				"id": "company_0002",
				"name": "MazuryCamp",
				"fc_website_url": null,
				"logo_image_url": null
			},
			"max_age": null,
			"min_age": null,
			"location": {
				"city": "",
				"street": "",
				"province": "",
				"post_code": "",
				"room_number": "",
				"house_number": ""
			},
			"food_type": null,
			"is_delete": false,
			"trip_type": null,
			"attributes": null,
			"company_id": "company_0002",
			"created_at": "2025-01-01T10:00:00.000Z",
			"food_vegan": null,
			"is_archive": false,
			"main_photo": {
				"id": "photo_0002",
				"url": "http://example.com/photo2.jpg",
				"width": 1700,
				"height": 1134,
				"provider": "cloudinary",
				"providerData": {}
			},
			"archived_at": null,
			"description": "Żeglarska przygoda 2025",
			"location_id": null,
			"country_code": "PL",
			"country_name": "Polska",
			"pickup_route": null,
			"published_at": null,
			"admin_comment": null,
			"category_code": null,
			"file_sections": null,
			"location_name": null,
			"transport_type": null,
			"food_vegetarian": null,
			"transport_route": null,
			"ag_state_version": 1,
			"food_description": null,
			"subcategory_code": null,
			"admin_approved_at": null,
			"transport_vehicle": null,
			"additional_info_text": null,
			"conditions_text_long": null,
			"schedule_description": null,
			"amenities_description": null,
			"conditions_text_short": null,
			"insurance_description": null,
			"transport_description": null,
			"admin_show_on_home_page": null,
			"participation_conditions": null,
			"participation_description": null,
			"admin_promote_on_home_page": null
		},
		"parent": {
			"id": "parent_0002",
			"city": "Gdańsk",
			"type": "PARENT",
			"email": "parent2@example.com",
			"pesel": null,
			"phone": "987654321",
			"street": "Ulica Morska",
			"illness": false,
			"alergies": false,
			"postcode": "80-001",
			"province": "pomorskie",
			"vaccines": null,
			"diagnosis": false,
			"full_name": "Tomasz Nowak",
			"is_delete": 0,
			"last_name": "Nowak",
			"medicines": false,
			"parent_id": null,
			"surgeries": false,
			"birth_date": null,
			"disability": false,
			"first_name": "Tomasz",
			"house_number": "20",
			"maladjustment": null,
			"owner_user_id": "cl67890fghij",
			"street_number": "20B",
			"medicines_dose": null,
			"medicines_name": null,
			"surgeries_date": null,
			"medicines_cause": null,
			"surgeries_cause": null,
			"ag_state_version": 1,
			"illness_symptoms": null,
			"alergies_symptoms": null,
			"other_information": null,
			"diagnosis_symptoms": null,
			"illness_description": null,
			"alergies_description": null,
			"diagnosis_description": null,
			"surgeries_desctiption": null,
			"disability_description": null,
			"maladjustment_description": null
		},
		"payment_due_date": "2025-07-01",
		"advance_payment_due_date": "2025-06-15",
		"payment_status": "REFUNDED",
		"advance_payment_status": "NOT_PAID",
		"advance_payment_price": 400,
		"start_date": "2025-07-10",
		"end_date": "2025-07-22",
		"base_price_per_person": 1500,
		"product_name": "Obóz Żeglarski 2025",
		"trip_name": "Obóz żeglarski na Mazurach",
		"user_name": "parent2@example.com",
		"company_name": "MazuryCamp",
		"type": "BOOKING",
		"rejection_reason": null,
		"rejection_description": null,
		"original_total_price": 1500,
		"original_advance_payment": 400,
		"trip_length_days": null,
		"participants_count": 1,
		"min_age": null,
		"max_age": null,
		"destination_province": null,
		"destination_description": null,
		"optional_trips": null,
		"inquiry_description": null,
		"month": null,
		"departure_date": null,
		"departure_time": null,
		"departure_address": null,
		"departure_remarks": null,
		"return_date": null,
		"return_time": null,
		"return_address": null,
		"return_remarks": null,
		"free_places_count": null,
		"transport_type": null,
		"transport_vehicle": null,
		"transport_price_per_person": null,
		"accommodation_place_id": null,
		"accommodation_price_per_person": null,
		"places": null,
		"inquiry_id": null,
		"quotation_id": null,
		"departure_place": null,
		"payment_mode": null,
		"product_type": null,
		"customer_phone": null,
		"customer_email": null,
		"initial_payment_amount": null,
		"paid_amount": null,
		"updated_at": null,
		"departure_place_price_per_pax": null,
		"departure_place_price_total": null,
		"advance_paid_at": null,
		"fully_paid_at": null,
		"payments": null,
		"liveness_status": "ACTIVE",
		"currency": "PLN",
		"is_fee_paid": false,
		"promo_code_id": null,
		"influencer_name": null,
		"trip": null,
		"product": null,
		"company": null,
		"type_label": "Rezerwacja",
		"status_label": "Oczekuje na zaliczkę"
	},
	{
		"id": "book_3001",
		"status": "ADVANCE_PAID",
		"user_id": "cl12345abcde",
		"trip_id": "trip_0001",
		"product_id": "IN_H1QHK1RSOD",
		"company_id": "company_0001",
		"participants": [
			{
				"id": "kid_0001",
				"city": "Warszawa",
				"type": "KID",
				"email": null,
				"pesel": "12345678901",
				"phone": null,
				"street": "Ulica ABC",
				"illness": false,
				"alergies": false,
				"postcode": "00-001",
				"province": "mazowieckie",
				"vaccines": [],
				"diagnosis": false,
				"full_name": "Adam Kowalski",
				"is_delete": 0,
				"last_name": "Kowalski",
				"medicines": false,
				"parent_id": null,
				"surgeries": false,
				"birth_date": "2020-01-01",
				"disability": false,
				"first_name": "Adam",
				"house_number": "10",
				"maladjustment": false,
				"owner_user_id": "cl12345abcde",
				"street_number": "5",
				"medicines_dose": null,
				"medicines_name": null,
				"surgeries_date": null,
				"medicines_cause": null,
				"surgeries_cause": null,
				"ag_state_version": 1,
				"illness_symptoms": null,
				"alergies_symptoms": null,
				"other_information": null,
				"diagnosis_symptoms": null,
				"illness_description": null,
				"alergies_description": null,
				"diagnosis_description": null,
				"surgeries_desctiption": null,
				"disability_description": null,
				"maladjustment_description": null
			}
		],
		"created_at": "2025-01-01T09:00:00.000Z",
		"total_price": 1200,
		"payable_price": 1200,
		"discount_amount": 0,
		"deleted_at": null,
		"ag_state_version": 3,
		"trip_data": {
			"id": "trip_0001",
			"name": "Kolonie w górach",
			"status": "ACTIVE",
			"advance": 300,
			"company": {
				"id": "company_0001",
				"name": "Górska Przygoda"
			},
			"max_age": 18,
			"min_age": 7,
			"product": {
				"id": "PR_0001",
				"name": "Kolonie 2025",
				"type": "kolonie"
			},
			"bookings": [],
			"end_date": "2025-07-15",
			"max_count": 10,
			"min_count": 1,
			"company_id": "company_0001",
			"created_at": "2024-12-01T09:00:00.000Z",
			"full_price": 1200,
			"is_deleted": false,
			"product_id": "PR_0001",
			"start_date": "2025-07-01",
			"archived_at": null,
			"is_archived": false,
			"product_type": "kolonie",
			"available_spots": 9,
			"ag_state_version": 1,
			"reservation_price": 1200,
			"advance_conditions": null,
			"reservation_min_days": null,
			"discounts_description": null,
			"full_price_conditions": null
		},
		"product_data": {
			"id": "IN_H1QHK1RSOD",
			"name": "Kolonie 2025",
			"type": "kolonie",
			"files": null,
			"media": null,
			"trips": [],
			"status": "ACTIVE",
			"company": {
				"id": "company_0001",
				"name": "Górska Przygoda",
				"fc_website_url": null,
				"logo_image_url": null
			},
			"max_age": 18,
			"min_age": 7,
			"location": {
				"city": "Zakopane",
				"street": "Ul. Górska",
				"province": "małopolskie",
				"post_code": "34-500",
				"room_number": "101",
				"house_number": "15"
			},
			"food_type": null,
			"is_delete": false,
			"trip_type": null,
			"attributes": null,
			"company_id": "company_0001",
			"created_at": "2024-12-01T09:00:00.000Z",
			"food_vegan": null,
			"is_archive": false,
			"main_photo": {
				"id": "photo_0001",
				"url": "http://example.com/photo1.jpg",
				"width": 1700,
				"height": 1134,
				"provider": "cloudinary",
				"providerData": {}
			},
			"archived_at": null,
			"description": "Kolonie w górach 2025",
			"location_id": null,
			"country_code": "PL",
			"country_name": "Polska",
			"pickup_route": null,
			"published_at": null,
			"admin_comment": null,
			"category_code": null,
			"file_sections": null,
			"location_name": null,
			"transport_type": "autokar",
			"food_vegetarian": null,
			"transport_route": null,
			"ag_state_version": 1,
			"food_description": null,
			"subcategory_code": null,
			"admin_approved_at": null,
			"transport_vehicle": "Mercedes-Benz Tourismo",
			"additional_info_text": null,
			"conditions_text_long": null,
			"schedule_description": null,
			"amenities_description": null,
			"conditions_text_short": null,
			"insurance_description": null,
			"transport_description": null,
			"admin_show_on_home_page": null,
			"participation_conditions": null,
			"participation_description": null,
			"admin_promote_on_home_page": null
		},
		"parent": {
			"id": "parent_0001",
			"city": "Warszawa",
			"type": "PARENT",
			"email": "rodzic@example.com",
			"pesel": null,
			"phone": "123456789",
			"street": "Ulica Nowa",
			"illness": false,
			"alergies": false,
			"postcode": "00-001",
			"province": "mazowieckie",
			"vaccines": null,
			"diagnosis": false,
			"full_name": "Jan Kowalski",
			"is_delete": 0,
			"last_name": "Kowalski",
			"medicines": false,
			"parent_id": null,
			"surgeries": false,
			"birth_date": null,
			"disability": false,
			"first_name": "Jan",
			"house_number": "5",
			"maladjustment": null,
			"owner_user_id": "cl12345abcde",
			"street_number": "5A",
			"medicines_dose": null,
			"medicines_name": null,
			"surgeries_date": null,
			"medicines_cause": null,
			"surgeries_cause": null,
			"ag_state_version": 1,
			"illness_symptoms": null,
			"alergies_symptoms": null,
			"other_information": null,
			"diagnosis_symptoms": null,
			"illness_description": null,
			"alergies_description": null,
			"diagnosis_description": null,
			"surgeries_desctiption": null,
			"disability_description": null,
			"maladjustment_description": null
		},
		"payment_due_date": "2025-06-15",
		"advance_payment_due_date": "2025-05-15",
		"payment_status": "UNPAID",
		"advance_payment_status": "NOT_PAID",
		"advance_payment_price": 300,
		"start_date": "2025-07-01",
		"end_date": "2025-07-15",
		"base_price_per_person": 1200,
		"product_name": "Kolonie 2025",
		"trip_name": "Kolonie w górach",
		"user_name": "rodzic@example.com",
		"company_name": "Górska Przygoda",
		"type": "BOOKING",
		"rejection_reason": null,
		"rejection_description": null,
		"original_total_price": 1200,
		"original_advance_payment": 300,
		"trip_length_days": 14,
		"participants_count": 1,
		"min_age": 7,
		"max_age": 18,
		"destination_province": "małopolskie",
		"destination_description": "Górska lokalizacja",
		"optional_trips": [],
		"inquiry_description": "",
		"month": "07",
		"departure_date": "2025-07-01",
		"departure_time": "08:00",
		"departure_address": "Dworzec PKP, Warszawa",
		"departure_remarks": "Zbiórka 30 minut przed odjazdem.",
		"return_date": "2025-07-15",
		"return_time": "18:00",
		"return_address": "Dworzec PKP, Warszawa",
		"return_remarks": "Powrót bezpośredni.",
		"free_places_count": 9,
		"transport_type": "autokar",
		"transport_vehicle": "Mercedes-Benz Tourismo",
		"transport_price_per_person": 50,
		"accommodation_place_id": "acc_001",
		"accommodation_price_per_person": 100,
		"places": [
			"Room 1"
		],
		"inquiry_id": "inq_001",
		"quotation_id": "quote_001",
		"departure_place": "Warszawa Centralna",
		"payment_mode": "online",
		"product_type": "kolonie",
		"customer_phone": "123456789",
		"customer_email": "rodzic@example.com",
		"initial_payment_amount": 300,
		"paid_amount": 300,
		"updated_at": "2025-01-02T10:00:00.000Z",
		"departure_place_price_per_pax": 10,
		"departure_place_price_total": 10,
		"advance_paid_at": "2025-01-02T10:05:00.000Z",
		"fully_paid_at": null,
		"payments": [
			{
				"id": "pay_001",
				"amount": 300,
				"date": "2025-01-02T10:05:00.000Z",
				"method": "card"
			}
		],
		"liveness_status": "ACTIVE",
		"currency": "PLN",
		"is_fee_paid": false,
		"promo_code_id": null,
		"influencer_name": null,
		"trip": null,
		"product": null,
		"company": null,
		"type_label": "Rezerwacja",
		"status_label": "Zaliczka Opłacona"
	},
	{
		"id": "book_006",
		"status": "CREATED",
		"user_id": "cl67890fghij",
		"trip_id": "trip_0002",
		"product_id": "IN_ABC123XYZ",
		"company_id": "company_0002",
		"participants": [
			{
				"id": "kid_0002",
				"city": "Gdańsk",
				"type": "KID",
				"email": null,
				"pesel": "98765432109",
				"phone": null,
				"street": "Ulica Morska",
				"illness": false,
				"alergies": false,
				"postcode": "80-001",
				"province": "pomorskie",
				"vaccines": [],
				"diagnosis": false,
				"full_name": "Anna Nowak",
				"is_delete": 0,
				"last_name": "Nowak",
				"medicines": false,
				"parent_id": null,
				"surgeries": false,
				"birth_date": "2015-06-15",
				"disability": false,
				"first_name": "Anna",
				"house_number": "20",
				"maladjustment": false,
				"owner_user_id": "cl67890fghij",
				"street_number": "20B",
				"medicines_dose": null,
				"medicines_name": null,
				"surgeries_date": null,
				"medicines_cause": null,
				"surgeries_cause": null,
				"ag_state_version": 1,
				"illness_symptoms": null,
				"alergies_symptoms": null,
				"other_information": null,
				"diagnosis_symptoms": null,
				"illness_description": null,
				"alergies_description": null,
				"diagnosis_description": null,
				"surgeries_desctiption": null,
				"disability_description": null,
				"maladjustment_description": null
			}
		],
		"created_at": "2025-02-01T10:30:00.000Z",
		"total_price": 1500,
		"payable_price": 1500,
		"discount_amount": null,
		"deleted_at": null,
		"ag_state_version": 1,
		"trip_data": {
			"id": "trip_0002",
			"name": "Obóz żeglarski na Mazurach",
			"status": "ACTIVE",
			"advance": 400,
			"company": {
				"id": "company_0002",
				"name": "MazuryCamp"
			},
			"max_age": 18,
			"min_age": 10,
			"product": {
				"id": "PR_0002",
				"name": "Obóz Żeglarski 2025",
				"type": "kolonie"
			},
			"bookings": [],
			"end_date": "2025-07-22",
			"max_count": 12,
			"min_count": 1,
			"company_id": "company_0002",
			"created_at": "2025-01-01T10:00:00.000Z",
			"full_price": 1500,
			"is_deleted": false,
			"product_id": "PR_0002",
			"start_date": "2025-07-10",
			"archived_at": null,
			"is_archived": false,
			"product_type": "kolonie",
			"available_spots": null,
			"ag_state_version": 1,
			"reservation_price": null,
			"advance_conditions": null,
			"reservation_min_days": null,
			"discounts_description": null,
			"full_price_conditions": null
		},
		"product_data": {
			"id": "PR_0002",
			"name": "Obóz Żeglarski 2025",
			"type": "kolonie",
			"files": null,
			"media": null,
			"trips": [],
			"status": "ACTIVE",
			"company": {
				"id": "company_0002",
				"name": "MazuryCamp",
				"fc_website_url": null,
				"logo_image_url": null
			},
			"max_age": null,
			"min_age": null,
			"location": {
				"city": "",
				"street": "",
				"province": "",
				"post_code": "",
				"room_number": "",
				"house_number": ""
			},
			"food_type": null,
			"is_delete": false,
			"trip_type": null,
			"attributes": null,
			"company_id": "company_0002",
			"created_at": "2025-01-01T10:00:00.000Z",
			"food_vegan": null,
			"is_archive": false,
			"main_photo": {
				"id": "photo_0002",
				"url": "http://example.com/photo2.jpg",
				"width": 1700,
				"height": 1134,
				"provider": "cloudinary",
				"providerData": {}
			},
			"archived_at": null,
			"description": "Żeglarska przygoda 2025",
			"location_id": null,
			"country_code": "PL",
			"country_name": "Polska",
			"pickup_route": null,
			"published_at": null,
			"admin_comment": null,
			"category_code": null,
			"file_sections": null,
			"location_name": null,
			"transport_type": null,
			"food_vegetarian": null,
			"transport_route": null,
			"ag_state_version": 1,
			"food_description": null,
			"subcategory_code": null,
			"admin_approved_at": null,
			"transport_vehicle": null,
			"additional_info_text": null,
			"conditions_text_long": null,
			"schedule_description": null,
			"amenities_description": null,
			"conditions_text_short": null,
			"insurance_description": null,
			"transport_description": null,
			"admin_show_on_home_page": null,
			"participation_conditions": null,
			"participation_description": null,
			"admin_promote_on_home_page": null
		},
		"parent": {
			"id": "parent_0002",
			"city": "Gdańsk",
			"type": "PARENT",
			"email": "parent2@example.com",
			"pesel": null,
			"phone": "987654321",
			"street": "Ulica Morska",
			"illness": false,
			"alergies": false,
			"postcode": "80-001",
			"province": "pomorskie",
			"vaccines": null,
			"diagnosis": false,
			"full_name": "Tomasz Nowak",
			"is_delete": 0,
			"last_name": "Nowak",
			"medicines": false,
			"parent_id": null,
			"surgeries": false,
			"birth_date": null,
			"disability": false,
			"first_name": "Tomasz",
			"house_number": "20",
			"maladjustment": null,
			"owner_user_id": "cl67890fghij",
			"street_number": "20B",
			"medicines_dose": null,
			"medicines_name": null,
			"surgeries_date": null,
			"medicines_cause": null,
			"surgeries_cause": null,
			"ag_state_version": 1,
			"illness_symptoms": null,
			"alergies_symptoms": null,
			"other_information": null,
			"diagnosis_symptoms": null,
			"illness_description": null,
			"alergies_description": null,
			"diagnosis_description": null,
			"surgeries_desctiption": null,
			"disability_description": null,
			"maladjustment_description": null
		},
		"payment_due_date": "2025-07-01",
		"advance_payment_due_date": "2025-06-15",
		"payment_status": "FAILED",
		"advance_payment_status": "NOT_PAID",
		"advance_payment_price": 400,
		"start_date": "2025-07-10",
		"end_date": "2025-07-22",
		"base_price_per_person": 1500,
		"product_name": "Obóz Żeglarski 2025",
		"trip_name": "Obóz żeglarski na Mazurach",
		"user_name": "parent2@example.com",
		"company_name": "MazuryCamp",
		"type": "BOOKING",
		"rejection_reason": null,
		"rejection_description": null,
		"original_total_price": 1500,
		"original_advance_payment": 400,
		"trip_length_days": null,
		"participants_count": 1,
		"min_age": null,
		"max_age": null,
		"destination_province": null,
		"destination_description": null,
		"optional_trips": null,
		"inquiry_description": null,
		"month": null,
		"departure_date": null,
		"departure_time": null,
		"departure_address": null,
		"departure_remarks": null,
		"return_date": null,
		"return_time": null,
		"return_address": null,
		"return_remarks": null,
		"free_places_count": null,
		"transport_type": null,
		"transport_vehicle": null,
		"transport_price_per_person": null,
		"accommodation_place_id": null,
		"accommodation_price_per_person": null,
		"places": null,
		"inquiry_id": null,
		"quotation_id": null,
		"departure_place": null,
		"payment_mode": null,
		"product_type": null,
		"customer_phone": null,
		"customer_email": null,
		"initial_payment_amount": null,
		"paid_amount": null,
		"updated_at": null,
		"departure_place_price_per_pax": null,
		"departure_place_price_total": null,
		"advance_paid_at": null,
		"fully_paid_at": null,
		"payments": null,
		"liveness_status": "ACTIVE",
		"currency": "PLN",
		"is_fee_paid": false,
		"promo_code_id": null,
		"influencer_name": null,
		"trip": null,
		"product": null,
		"company": null,
		"type_label": "Rezerwacja",
		"status_label": "Oczekuje na zaliczkę"
	},
	{
		"id": "book_312002",
		"status": "ADVANCE_PAID",
		"user_id": "cl12345abcde",
		"trip_id": "trip_0001",
		"product_id": "IN_ABC123XYZ",
		"company_id": "company_0001",
		"participants": [
			{
				"id": "kid_0001",
				"city": "Warszawa",
				"type": "KID",
				"email": null,
				"pesel": "12345678901",
				"phone": null,
				"street": "Ulica ABC",
				"illness": false,
				"alergies": false,
				"postcode": "00-001",
				"province": "mazowieckie",
				"vaccines": [],
				"diagnosis": false,
				"full_name": "Adam Kowalski",
				"is_delete": 0,
				"last_name": "Kowalski",
				"medicines": false,
				"parent_id": null,
				"surgeries": false,
				"birth_date": "2020-01-01",
				"disability": false,
				"first_name": "Adam",
				"house_number": "10",
				"maladjustment": false,
				"owner_user_id": "cl12345abcde",
				"street_number": "5",
				"medicines_dose": null,
				"medicines_name": null,
				"surgeries_date": null,
				"medicines_cause": null,
				"surgeries_cause": null,
				"ag_state_version": 1,
				"illness_symptoms": null,
				"alergies_symptoms": null,
				"other_information": null,
				"diagnosis_symptoms": null,
				"illness_description": null,
				"alergies_description": null,
				"diagnosis_description": null,
				"surgeries_desctiption": null,
				"disability_description": null,
				"maladjustment_description": null
			},
			{
				"id": "kid_0001",
				"city": "Warszawa",
				"type": "KID",
				"email": null,
				"pesel": "12345678901",
				"phone": null,
				"street": "Ulica ABC",
				"illness": false,
				"alergies": false,
				"postcode": "00-001",
				"province": "mazowieckie",
				"vaccines": [],
				"diagnosis": false,
				"full_name": "Adam Kowalski",
				"is_delete": 0,
				"last_name": "Kowalski",
				"medicines": false,
				"parent_id": null,
				"surgeries": false,
				"birth_date": "2020-01-01",
				"disability": false,
				"first_name": "Adam",
				"house_number": "10",
				"maladjustment": false,
				"owner_user_id": "cl12345abcde",
				"street_number": "5",
				"medicines_dose": null,
				"medicines_name": null,
				"surgeries_date": null,
				"medicines_cause": null,
				"surgeries_cause": null,
				"ag_state_version": 1,
				"illness_symptoms": null,
				"alergies_symptoms": null,
				"other_information": null,
				"diagnosis_symptoms": null,
				"illness_description": null,
				"alergies_description": null,
				"diagnosis_description": null,
				"surgeries_desctiption": null,
				"disability_description": null,
				"maladjustment_description": null
			},
			{
				"id": "kid_0001",
				"city": "Warszawa",
				"type": "KID",
				"email": null,
				"pesel": "12345678901",
				"phone": null,
				"street": "Ulica ABC",
				"illness": false,
				"alergies": false,
				"postcode": "00-001",
				"province": "mazowieckie",
				"vaccines": [],
				"diagnosis": false,
				"full_name": "Adam Kowalski",
				"is_delete": 0,
				"last_name": "Kowalski",
				"medicines": false,
				"parent_id": null,
				"surgeries": false,
				"birth_date": "2020-01-01",
				"disability": false,
				"first_name": "Adam",
				"house_number": "10",
				"maladjustment": false,
				"owner_user_id": "cl12345abcde",
				"street_number": "5",
				"medicines_dose": null,
				"medicines_name": null,
				"surgeries_date": null,
				"medicines_cause": null,
				"surgeries_cause": null,
				"ag_state_version": 1,
				"illness_symptoms": null,
				"alergies_symptoms": null,
				"other_information": null,
				"diagnosis_symptoms": null,
				"illness_description": null,
				"alergies_description": null,
				"diagnosis_description": null,
				"surgeries_desctiption": null,
				"disability_description": null,
				"maladjustment_description": null
			},
			{
				"id": "kid_0001",
				"city": "Warszawa",
				"type": "KID",
				"email": null,
				"pesel": "12345678901",
				"phone": null,
				"street": "Ulica ABC",
				"illness": false,
				"alergies": false,
				"postcode": "00-001",
				"province": "mazowieckie",
				"vaccines": [],
				"diagnosis": false,
				"full_name": "Adam Kowalski",
				"is_delete": 0,
				"last_name": "Kowalski",
				"medicines": false,
				"parent_id": null,
				"surgeries": false,
				"birth_date": "2020-01-01",
				"disability": false,
				"first_name": "Adam",
				"house_number": "10",
				"maladjustment": false,
				"owner_user_id": "cl12345abcde",
				"street_number": "5",
				"medicines_dose": null,
				"medicines_name": null,
				"surgeries_date": null,
				"medicines_cause": null,
				"surgeries_cause": null,
				"ag_state_version": 1,
				"illness_symptoms": null,
				"alergies_symptoms": null,
				"other_information": null,
				"diagnosis_symptoms": null,
				"illness_description": null,
				"alergies_description": null,
				"diagnosis_description": null,
				"surgeries_desctiption": null,
				"disability_description": null,
				"maladjustment_description": null
			}
		],
		"created_at": "2025-01-01T09:00:00.000Z",
		"total_price": 1200,
		"payable_price": 1200,
		"discount_amount": null,
		"deleted_at": null,
		"ag_state_version": 3,
		"trip_data": {
			"id": "trip_0001",
			"name": "Kolonie w górach",
			"status": "ACTIVE",
			"advance": 300,
			"company": {
				"id": "company_0001",
				"name": "Górska Przygoda"
			},
			"max_age": 18,
			"min_age": 7,
			"product": {
				"id": "PR_0001",
				"name": "Kolonie 2025",
				"type": "kolonie"
			},
			"bookings": [],
			"end_date": "2025-07-15",
			"max_count": 10,
			"min_count": 1,
			"company_id": "company_0001",
			"created_at": "2024-12-01T09:00:00.000Z",
			"full_price": 1200,
			"is_deleted": false,
			"product_id": "PR_0001",
			"start_date": "2025-07-01",
			"archived_at": null,
			"is_archived": false,
			"product_type": "kolonie",
			"available_spots": null,
			"ag_state_version": 1,
			"reservation_price": null,
			"advance_conditions": null,
			"reservation_min_days": null,
			"discounts_description": null,
			"full_price_conditions": null
		},
		"product_data": {
			"id": "IN_H1QHK1RSOD",
			"name": "Kolonie 2025",
			"type": "kolonie",
			"files": null,
			"media": null,
			"trips": [],
			"status": "ACTIVE",
			"company": {
				"id": "company_0001",
				"name": "Górska Przygoda",
				"fc_website_url": null,
				"logo_image_url": null
			},
			"max_age": null,
			"min_age": null,
			"location": {
				"city": "",
				"street": "",
				"province": "",
				"post_code": "",
				"room_number": "",
				"house_number": ""
			},
			"food_type": null,
			"is_delete": false,
			"trip_type": null,
			"attributes": null,
			"company_id": "company_0001",
			"created_at": "2024-12-01T09:00:00.000Z",
			"food_vegan": null,
			"is_archive": false,
			"main_photo": {
				"id": "photo_0001",
				"url": "http://example.com/photo1.jpg",
				"width": 1700,
				"height": 1134,
				"provider": "cloudinary",
				"providerData": {}
			},
			"archived_at": null,
			"description": "Kolonie w górach 2025",
			"location_id": null,
			"country_code": "PL",
			"country_name": "Polska",
			"pickup_route": null,
			"published_at": null,
			"admin_comment": null,
			"category_code": null,
			"file_sections": null,
			"location_name": null,
			"transport_type": null,
			"food_vegetarian": null,
			"transport_route": null,
			"ag_state_version": 1,
			"food_description": null,
			"subcategory_code": null,
			"admin_approved_at": null,
			"transport_vehicle": null,
			"additional_info_text": null,
			"conditions_text_long": null,
			"schedule_description": null,
			"amenities_description": null,
			"conditions_text_short": null,
			"insurance_description": null,
			"transport_description": null,
			"admin_show_on_home_page": null,
			"participation_conditions": null,
			"participation_description": null,
			"admin_promote_on_home_page": null
		},
		"parent": {
			"id": "parent_0001",
			"city": "Warszawa",
			"type": "PARENT",
			"email": "rodzic@example.com",
			"pesel": null,
			"phone": "123456789",
			"street": "Ulica Nowa",
			"illness": false,
			"alergies": false,
			"postcode": "00-001",
			"province": "mazowieckie",
			"vaccines": null,
			"diagnosis": false,
			"full_name": "Jan Kowalski",
			"is_delete": 0,
			"last_name": "Kowalski",
			"medicines": false,
			"parent_id": null,
			"surgeries": false,
			"birth_date": null,
			"disability": false,
			"first_name": "Jan",
			"house_number": "5",
			"maladjustment": null,
			"owner_user_id": "cl12345abcde",
			"street_number": "5A",
			"medicines_dose": null,
			"medicines_name": null,
			"surgeries_date": null,
			"medicines_cause": null,
			"surgeries_cause": null,
			"ag_state_version": 1,
			"illness_symptoms": null,
			"alergies_symptoms": null,
			"other_information": null,
			"diagnosis_symptoms": null,
			"illness_description": null,
			"alergies_description": null,
			"diagnosis_description": null,
			"surgeries_desctiption": null,
			"disability_description": null,
			"maladjustment_description": null
		},
		"payment_due_date": "2025-06-15",
		"advance_payment_due_date": "2025-05-15",
		"payment_status": "PAID",
		"advance_payment_status": "NOT_PAID",
		"advance_payment_price": 300,
		"start_date": "2025-07-01",
		"end_date": "2025-07-15",
		"base_price_per_person": 1200,
		"product_name": "Kolonie 2025",
		"trip_name": "Kolonie w górach",
		"user_name": "rodzic@example.com",
		"company_name": "Górska Przygoda",
		"type": "BOOKING",
		"rejection_reason": null,
		"rejection_description": null,
		"original_total_price": 1200,
		"original_advance_payment": 300,
		"trip_length_days": null,
		"participants_count": 1,
		"min_age": null,
		"max_age": null,
		"destination_province": null,
		"destination_description": null,
		"optional_trips": null,
		"inquiry_description": null,
		"month": null,
		"departure_date": null,
		"departure_time": null,
		"departure_address": null,
		"departure_remarks": null,
		"return_date": null,
		"return_time": null,
		"return_address": null,
		"return_remarks": null,
		"free_places_count": null,
		"transport_type": null,
		"transport_vehicle": null,
		"transport_price_per_person": null,
		"accommodation_place_id": null,
		"accommodation_price_per_person": null,
		"places": null,
		"inquiry_id": null,
		"quotation_id": null,
		"departure_place": null,
		"payment_mode": null,
		"product_type": null,
		"customer_phone": null,
		"customer_email": null,
		"initial_payment_amount": null,
		"paid_amount": null,
		"updated_at": null,
		"departure_place_price_per_pax": null,
		"departure_place_price_total": null,
		"advance_paid_at": null,
		"fully_paid_at": null,
		"payments": null,
		"liveness_status": "ACTIVE",
		"currency": "PLN",
		"is_fee_paid": false,
		"promo_code_id": null,
		"influencer_name": null,
		"trip": null,
		"product": null,
		"company": null,
		"type_label": "Rezerwacja",
		"status_label": "Zaliczka Opłacona"
	},
	{
		"id": "asd12",
		"status": "CREATED",
		"user_id": "cl67890fghij",
		"trip_id": "trip_0002",
		"product_id": "IN_ABC123XYZ",
		"company_id": "company_0002",
		"participants": [
			{
				"id": "kid_0002",
				"city": "Gdańsk",
				"type": "KID",
				"email": null,
				"pesel": "98765432109",
				"phone": null,
				"street": "Ulica Morska",
				"illness": false,
				"alergies": false,
				"postcode": "80-001",
				"province": "pomorskie",
				"vaccines": [],
				"diagnosis": false,
				"full_name": "Anna Nowak",
				"is_delete": 0,
				"last_name": "Nowak",
				"medicines": false,
				"parent_id": null,
				"surgeries": false,
				"birth_date": "2015-06-15",
				"disability": false,
				"first_name": "Anna",
				"house_number": "20",
				"maladjustment": false,
				"owner_user_id": "cl67890fghij",
				"street_number": "20B",
				"medicines_dose": null,
				"medicines_name": null,
				"surgeries_date": null,
				"medicines_cause": null,
				"surgeries_cause": null,
				"ag_state_version": 1,
				"illness_symptoms": null,
				"alergies_symptoms": null,
				"other_information": null,
				"diagnosis_symptoms": null,
				"illness_description": null,
				"alergies_description": null,
				"diagnosis_description": null,
				"surgeries_desctiption": null,
				"disability_description": null,
				"maladjustment_description": null
			}
		],
		"created_at": "2025-02-01T10:30:00.000Z",
		"total_price": 1500,
		"payable_price": 1500,
		"discount_amount": null,
		"deleted_at": null,
		"ag_state_version": 1,
		"trip_data": {
			"id": "trip_0002",
			"name": "Obóz żeglarski na Mazurach",
			"status": "ACTIVE",
			"advance": 400,
			"company": {
				"id": "company_0002",
				"name": "MazuryCamp"
			},
			"max_age": 18,
			"min_age": 10,
			"product": {
				"id": "PR_0002",
				"name": "Obóz Żeglarski 2025",
				"type": "kolonie"
			},
			"bookings": [],
			"end_date": "2025-07-22",
			"max_count": 12,
			"min_count": 1,
			"company_id": "company_0002",
			"created_at": "2025-01-01T10:00:00.000Z",
			"full_price": 1500,
			"is_deleted": false,
			"product_id": "PR_0002",
			"start_date": "2025-07-10",
			"archived_at": null,
			"is_archived": false,
			"product_type": "kolonie",
			"available_spots": null,
			"ag_state_version": 1,
			"reservation_price": null,
			"advance_conditions": null,
			"reservation_min_days": null,
			"discounts_description": null,
			"full_price_conditions": null
		},
		"product_data": {
			"id": "PR_0002",
			"name": "Obóz Żeglarski 2025",
			"type": "kolonie",
			"files": null,
			"media": null,
			"trips": [],
			"status": "ACTIVE",
			"company": {
				"id": "company_0002",
				"name": "MazuryCamp",
				"fc_website_url": null,
				"logo_image_url": null
			},
			"max_age": null,
			"min_age": null,
			"location": {
				"city": "",
				"street": "",
				"province": "",
				"post_code": "",
				"room_number": "",
				"house_number": ""
			},
			"food_type": null,
			"is_delete": false,
			"trip_type": null,
			"attributes": null,
			"company_id": "company_0002",
			"created_at": "2025-01-01T10:00:00.000Z",
			"food_vegan": null,
			"is_archive": false,
			"main_photo": {
				"id": "photo_0002",
				"url": "http://example.com/photo2.jpg",
				"width": 1700,
				"height": 1134,
				"provider": "cloudinary",
				"providerData": {}
			},
			"archived_at": null,
			"description": "Żeglarska przygoda 2025",
			"location_id": null,
			"country_code": "PL",
			"country_name": "Polska",
			"pickup_route": null,
			"published_at": null,
			"admin_comment": null,
			"category_code": null,
			"file_sections": null,
			"location_name": null,
			"transport_type": null,
			"food_vegetarian": null,
			"transport_route": null,
			"ag_state_version": 1,
			"food_description": null,
			"subcategory_code": null,
			"admin_approved_at": null,
			"transport_vehicle": null,
			"additional_info_text": null,
			"conditions_text_long": null,
			"schedule_description": null,
			"amenities_description": null,
			"conditions_text_short": null,
			"insurance_description": null,
			"transport_description": null,
			"admin_show_on_home_page": null,
			"participation_conditions": null,
			"participation_description": null,
			"admin_promote_on_home_page": null
		},
		"parent": {
			"id": "parent_0002",
			"city": "Gdańsk",
			"type": "PARENT",
			"email": "parent2@example.com",
			"pesel": null,
			"phone": "987654321",
			"street": "Ulica Morska",
			"illness": false,
			"alergies": false,
			"postcode": "80-001",
			"province": "pomorskie",
			"vaccines": null,
			"diagnosis": false,
			"full_name": "Tomasz Nowak",
			"is_delete": 0,
			"last_name": "Nowak",
			"medicines": false,
			"parent_id": null,
			"surgeries": false,
			"birth_date": null,
			"disability": false,
			"first_name": "Tomasz",
			"house_number": "20",
			"maladjustment": null,
			"owner_user_id": "cl67890fghij",
			"street_number": "20B",
			"medicines_dose": null,
			"medicines_name": null,
			"surgeries_date": null,
			"medicines_cause": null,
			"surgeries_cause": null,
			"ag_state_version": 1,
			"illness_symptoms": null,
			"alergies_symptoms": null,
			"other_information": null,
			"diagnosis_symptoms": null,
			"illness_description": null,
			"alergies_description": null,
			"diagnosis_description": null,
			"surgeries_desctiption": null,
			"disability_description": null,
			"maladjustment_description": null
		},
		"payment_due_date": "2025-07-01",
		"advance_payment_due_date": "2025-06-15",
		"payment_status": "REFUNDED",
		"advance_payment_status": "NOT_PAID",
		"advance_payment_price": 400,
		"start_date": "2025-07-10",
		"end_date": "2025-07-22",
		"base_price_per_person": 1500,
		"product_name": "Obóz Żeglarski 2025",
		"trip_name": "Obóz żeglarski na Mazurach",
		"user_name": "parent2@example.com",
		"company_name": "MazuryCamp",
		"type": "BOOKING",
		"rejection_reason": null,
		"rejection_description": null,
		"original_total_price": 1500,
		"original_advance_payment": 400,
		"trip_length_days": null,
		"participants_count": 1,
		"min_age": null,
		"max_age": null,
		"destination_province": null,
		"destination_description": null,
		"optional_trips": null,
		"inquiry_description": null,
		"month": null,
		"departure_date": null,
		"departure_time": null,
		"departure_address": null,
		"departure_remarks": null,
		"return_date": null,
		"return_time": null,
		"return_address": null,
		"return_remarks": null,
		"free_places_count": null,
		"transport_type": null,
		"transport_vehicle": null,
		"transport_price_per_person": null,
		"accommodation_place_id": null,
		"accommodation_price_per_person": null,
		"places": null,
		"inquiry_id": null,
		"quotation_id": null,
		"departure_place": null,
		"payment_mode": null,
		"product_type": null,
		"customer_phone": null,
		"customer_email": null,
		"initial_payment_amount": null,
		"paid_amount": null,
		"updated_at": null,
		"departure_place_price_per_pax": null,
		"departure_place_price_total": null,
		"advance_paid_at": null,
		"fully_paid_at": null,
		"payments": null,
		"liveness_status": "ACTIVE",
		"currency": "PLN",
		"is_fee_paid": false,
		"promo_code_id": null,
		"influencer_name": null,
		"trip": null,
		"product": null,
		"company": null,
		"type_label": "Rezerwacja",
		"status_label": "Oczekuje na zaliczkę"
	}
]